<?xml version="1.0" encoding="UTF-8"?>
<export version="E">
  <design>
    <source>C:\Users\HPz420\Documents\GitHub\land-boards\lb-boards\SYNTHS\ER-MIDI-CV4-02_SET\ER-MIDI-CV4-02_DB\ER-MIDI-CV4-02_DB.kicad_sch</source>
    <date>11/2/2022 3:50:04 PM</date>
    <tool>Eeschema (6.0.1)</tool>
    <sheet number="1" name="/" tstamps="/">
      <title_block>
        <title>SYNTH MIDI CONTROLLER</title>
        <company>LAND BOARDS LLC</company>
        <rev>1</rev>
        <date>2022-11-01</date>
        <source>ER-MIDI-CV4-02_DB.kicad_sch</source>
        <comment number="1" value="https://note.com/solder_state/n/n17e028497eba"/>
        <comment number="2" value=""/>
        <comment number="3" value=""/>
        <comment number="4" value=""/>
        <comment number="5" value=""/>
        <comment number="6" value=""/>
        <comment number="7" value=""/>
        <comment number="8" value=""/>
        <comment number="9" value=""/>
      </title_block>
    </sheet>
  </design>
  <components>
    <comp ref="C1">
      <value>0.1uF</value>
      <footprint>Capacitor_THT:C_Rect_L4.0mm_W2.5mm_P2.50mm</footprint>
      <libsource lib="Device" part="C" description="Unpolarized capacitor"/>
      <property name="Sheetname" value=""/>
      <property name="Sheetfile" value="ER-MIDI-CV4-02_DB.kicad_sch"/>
      <sheetpath names="/" tstamps="/"/>
      <tstamps>5b344dd7-44e4-417f-8dd5-bae719936934</tstamps>
    </comp>
    <comp ref="C2">
      <value>0.1uF</value>
      <footprint>Capacitor_THT:C_Rect_L4.0mm_W2.5mm_P2.50mm</footprint>
      <libsource lib="Device" part="C" description="Unpolarized capacitor"/>
      <property name="Sheetname" value=""/>
      <property name="Sheetfile" value="ER-MIDI-CV4-02_DB.kicad_sch"/>
      <sheetpath names="/" tstamps="/"/>
      <tstamps>4497858e-0b02-45fb-9ef6-8285d34c751e</tstamps>
    </comp>
    <comp ref="C3">
      <value>0.1uF</value>
      <footprint>Capacitor_THT:C_Rect_L4.0mm_W2.5mm_P2.50mm</footprint>
      <libsource lib="Device" part="C" description="Unpolarized capacitor"/>
      <property name="Sheetname" value=""/>
      <property name="Sheetfile" value="ER-MIDI-CV4-02_DB.kicad_sch"/>
      <sheetpath names="/" tstamps="/"/>
      <tstamps>82df91bd-b1f7-4cb5-a4b8-f014077ed225</tstamps>
    </comp>
    <comp ref="C4">
      <value>0.1uF</value>
      <footprint>Capacitor_THT:C_Rect_L4.0mm_W2.5mm_P2.50mm</footprint>
      <libsource lib="Device" part="C" description="Unpolarized capacitor"/>
      <property name="Sheetname" value=""/>
      <property name="Sheetfile" value="ER-MIDI-CV4-02_DB.kicad_sch"/>
      <sheetpath names="/" tstamps="/"/>
      <tstamps>ced9c057-ce14-4720-9155-5725ea0236ff</tstamps>
    </comp>
    <comp ref="D1">
      <value>BAT41</value>
      <footprint>Diode_THT:D_DO-35_SOD27_P2.54mm_Vertical_KathodeUp</footprint>
      <libsource lib="Device" part="D_Schottky" description="Schottky diode"/>
      <property name="Sheetname" value=""/>
      <property name="Sheetfile" value="ER-MIDI-CV4-02_DB.kicad_sch"/>
      <sheetpath names="/" tstamps="/"/>
      <tstamps>5d1d6cdc-7179-40c2-adea-bb5b15d5e654</tstamps>
    </comp>
    <comp ref="D2">
      <value>BAT41</value>
      <footprint>Diode_THT:D_DO-35_SOD27_P2.54mm_Vertical_KathodeUp</footprint>
      <libsource lib="Device" part="D_Schottky" description="Schottky diode"/>
      <property name="Sheetname" value=""/>
      <property name="Sheetfile" value="ER-MIDI-CV4-02_DB.kicad_sch"/>
      <sheetpath names="/" tstamps="/"/>
      <tstamps>659bf2f5-347c-4504-b276-84660e67d850</tstamps>
    </comp>
    <comp ref="D3">
      <value>BAT41</value>
      <footprint>Diode_THT:D_DO-35_SOD27_P2.54mm_Vertical_KathodeUp</footprint>
      <libsource lib="Device" part="D_Schottky" description="Schottky diode"/>
      <property name="Sheetname" value=""/>
      <property name="Sheetfile" value="ER-MIDI-CV4-02_DB.kicad_sch"/>
      <sheetpath names="/" tstamps="/"/>
      <tstamps>6b2a283c-c8a8-4e58-991b-ae62c9dcb7a6</tstamps>
    </comp>
    <comp ref="D4">
      <value>BAT41</value>
      <footprint>Diode_THT:D_DO-35_SOD27_P2.54mm_Vertical_KathodeUp</footprint>
      <libsource lib="Device" part="D_Schottky" description="Schottky diode"/>
      <property name="Sheetname" value=""/>
      <property name="Sheetfile" value="ER-MIDI-CV4-02_DB.kicad_sch"/>
      <sheetpath names="/" tstamps="/"/>
      <tstamps>7f518ad4-ea6c-4699-8b9f-9c729df5a7a9</tstamps>
    </comp>
    <comp ref="D5">
      <value>BAT41</value>
      <footprint>Diode_THT:D_DO-35_SOD27_P2.54mm_Vertical_KathodeUp</footprint>
      <libsource lib="Device" part="D_Schottky" description="Schottky diode"/>
      <property name="Sheetname" value=""/>
      <property name="Sheetfile" value="ER-MIDI-CV4-02_DB.kicad_sch"/>
      <sheetpath names="/" tstamps="/"/>
      <tstamps>22938b05-3f83-449a-95d3-1b54d307d63e</tstamps>
    </comp>
    <comp ref="D6">
      <value>BAT41</value>
      <footprint>Diode_THT:D_DO-35_SOD27_P2.54mm_Vertical_KathodeUp</footprint>
      <libsource lib="Device" part="D_Schottky" description="Schottky diode"/>
      <property name="Sheetname" value=""/>
      <property name="Sheetfile" value="ER-MIDI-CV4-02_DB.kicad_sch"/>
      <sheetpath names="/" tstamps="/"/>
      <tstamps>fc75b38a-6926-42e2-ae6a-814cb614c620</tstamps>
    </comp>
    <comp ref="D7">
      <value>BAT41</value>
      <footprint>Diode_THT:D_DO-35_SOD27_P2.54mm_Vertical_KathodeUp</footprint>
      <libsource lib="Device" part="D_Schottky" description="Schottky diode"/>
      <property name="Sheetname" value=""/>
      <property name="Sheetfile" value="ER-MIDI-CV4-02_DB.kicad_sch"/>
      <sheetpath names="/" tstamps="/"/>
      <tstamps>03aec349-f4c0-43d8-a745-af6e85623524</tstamps>
    </comp>
    <comp ref="D8">
      <value>BAT41</value>
      <footprint>Diode_THT:D_DO-35_SOD27_P2.54mm_Vertical_KathodeUp</footprint>
      <libsource lib="Device" part="D_Schottky" description="Schottky diode"/>
      <property name="Sheetname" value=""/>
      <property name="Sheetfile" value="ER-MIDI-CV4-02_DB.kicad_sch"/>
      <sheetpath names="/" tstamps="/"/>
      <tstamps>4d573c2b-bc6f-41d3-b161-7bbf532658e5</tstamps>
    </comp>
    <comp ref="D9">
      <value>BAT41</value>
      <footprint>Diode_THT:D_DO-35_SOD27_P2.54mm_Vertical_KathodeUp</footprint>
      <libsource lib="Device" part="D_Schottky" description="Schottky diode"/>
      <property name="Sheetname" value=""/>
      <property name="Sheetfile" value="ER-MIDI-CV4-02_DB.kicad_sch"/>
      <sheetpath names="/" tstamps="/"/>
      <tstamps>47a35921-d24d-4485-9108-eed5a848a207</tstamps>
    </comp>
    <comp ref="D10">
      <value>BAT41</value>
      <footprint>Diode_THT:D_DO-35_SOD27_P2.54mm_Vertical_KathodeUp</footprint>
      <libsource lib="Device" part="D_Schottky" description="Schottky diode"/>
      <property name="Sheetname" value=""/>
      <property name="Sheetfile" value="ER-MIDI-CV4-02_DB.kicad_sch"/>
      <sheetpath names="/" tstamps="/"/>
      <tstamps>da76a4a9-313a-49a4-8b32-cf2a930d79fa</tstamps>
    </comp>
    <comp ref="D11">
      <value>BAT41</value>
      <footprint>Diode_THT:D_DO-35_SOD27_P2.54mm_Vertical_KathodeUp</footprint>
      <libsource lib="Device" part="D_Schottky" description="Schottky diode"/>
      <property name="Sheetname" value=""/>
      <property name="Sheetfile" value="ER-MIDI-CV4-02_DB.kicad_sch"/>
      <sheetpath names="/" tstamps="/"/>
      <tstamps>7b035b14-3bb9-4006-b86b-d523a7a87493</tstamps>
    </comp>
    <comp ref="D12">
      <value>BAT41</value>
      <footprint>Diode_THT:D_DO-35_SOD27_P2.54mm_Vertical_KathodeUp</footprint>
      <libsource lib="Device" part="D_Schottky" description="Schottky diode"/>
      <property name="Sheetname" value=""/>
      <property name="Sheetfile" value="ER-MIDI-CV4-02_DB.kicad_sch"/>
      <sheetpath names="/" tstamps="/"/>
      <tstamps>796b3a68-a26d-4767-a9e9-76c1428b1aa3</tstamps>
    </comp>
    <comp ref="D13">
      <value>BAT41</value>
      <footprint>Diode_THT:D_DO-35_SOD27_P7.62mm_Horizontal</footprint>
      <datasheet>https://www.mouser.com/ProductDetail/onsemi-Fairchild/1N4148?qs=i4Fj9T%2FoRm8RMUhj5DeFQg%3D%3D</datasheet>
      <libsource lib="LandBoards_Semis" part="DIODESCH-fixed" description=""/>
      <property name="Sheetname" value=""/>
      <property name="Sheetfile" value="ER-MIDI-CV4-02_DB.kicad_sch"/>
      <sheetpath names="/" tstamps="/"/>
      <tstamps>8164b2c8-3395-4d99-a9e9-f5400e3a1d2e</tstamps>
    </comp>
    <comp ref="J1">
      <value>CONN, IDC, 2X5</value>
      <footprint>Connector_IDC:IDC-Header_2x05_P2.54mm_Vertical</footprint>
      <libsource lib="Connector_Generic" part="Conn_02x05_Odd_Even" description="Generic connector, double row, 02x05, odd/even pin numbering scheme (row 1 odd numbers, row 2 even numbers), script generated (kicad-library-utils/schlib/autogen/connector/)"/>
      <property name="Sheetname" value=""/>
      <property name="Sheetfile" value="ER-MIDI-CV4-02_DB.kicad_sch"/>
      <sheetpath names="/" tstamps="/"/>
      <tstamps>d813b2e0-7ae4-43e2-8b74-0f1f3ecea957</tstamps>
    </comp>
    <comp ref="J2">
      <value>HEADER, STRT, 1x10</value>
      <footprint>Connector_PinHeader_2.54mm:PinHeader_1x10_P2.54mm_Vertical</footprint>
      <libsource lib="Connector_Generic" part="Conn_01x10" description="Generic connector, single row, 01x10, script generated (kicad-library-utils/schlib/autogen/connector/)"/>
      <property name="Sheetname" value=""/>
      <property name="Sheetfile" value="ER-MIDI-CV4-02_DB.kicad_sch"/>
      <sheetpath names="/" tstamps="/"/>
      <tstamps>9c2a45bf-eecb-4bb8-976d-6f822d56418a</tstamps>
    </comp>
    <comp ref="J3">
      <value>Conn_01x04</value>
      <footprint>Connector_PinHeader_2.54mm:PinHeader_1x04_P2.54mm_Vertical</footprint>
      <libsource lib="Connector_Generic" part="Conn_01x04" description="Generic connector, single row, 01x04, script generated (kicad-library-utils/schlib/autogen/connector/)"/>
      <property name="Sheetname" value=""/>
      <property name="Sheetfile" value="ER-MIDI-CV4-02_DB.kicad_sch"/>
      <sheetpath names="/" tstamps="/"/>
      <tstamps>22999043-2d62-4a5e-b586-1396e4c13a5c</tstamps>
    </comp>
    <comp ref="J4">
      <value>HEADER, STRT, 1x4</value>
      <footprint>Connector_PinHeader_2.54mm:PinHeader_1x04_P2.54mm_Vertical</footprint>
      <libsource lib="Connector_Generic" part="Conn_01x04" description="Generic connector, single row, 01x04, script generated (kicad-library-utils/schlib/autogen/connector/)"/>
      <property name="Sheetname" value=""/>
      <property name="Sheetfile" value="ER-MIDI-CV4-02_DB.kicad_sch"/>
      <sheetpath names="/" tstamps="/"/>
      <tstamps>f1c2fb42-4576-4f1b-9df0-15ed5099ca14</tstamps>
    </comp>
    <comp ref="J5">
      <value>HEADER, STRT, 1x2</value>
      <footprint>Connector_PinHeader_2.54mm:PinHeader_1x02_P2.54mm_Vertical</footprint>
      <libsource lib="Connector_Generic" part="Conn_01x02" description="Generic connector, single row, 01x02, script generated (kicad-library-utils/schlib/autogen/connector/)"/>
      <property name="Sheetname" value=""/>
      <property name="Sheetfile" value="ER-MIDI-CV4-02_DB.kicad_sch"/>
      <sheetpath names="/" tstamps="/"/>
      <tstamps>309e2839-3c95-45df-b7ac-fa723f3d94a2</tstamps>
    </comp>
    <comp ref="Q1">
      <value>2N3904</value>
      <footprint>Package_TO_SOT_THT:TO-92_Inline</footprint>
      <datasheet>https://www.onsemi.com/pub/Collateral/2N3903-D.PDF</datasheet>
      <libsource lib="Transistor_BJT" part="2N3904" description="0.2A Ic, 40V Vce, Small Signal NPN Transistor, TO-92"/>
      <property name="Sheetname" value=""/>
      <property name="Sheetfile" value="ER-MIDI-CV4-02_DB.kicad_sch"/>
      <sheetpath names="/" tstamps="/"/>
      <tstamps>f3ca30a8-8e7b-4ca7-9eef-98002b3a5ee1</tstamps>
    </comp>
    <comp ref="R1">
      <value>2.2K</value>
      <footprint>Resistor_THT:R_Axial_DIN0204_L3.6mm_D1.6mm_P2.54mm_Vertical</footprint>
      <libsource lib="Device" part="R" description="Resistor"/>
      <property name="Sheetname" value=""/>
      <property name="Sheetfile" value="ER-MIDI-CV4-02_DB.kicad_sch"/>
      <sheetpath names="/" tstamps="/"/>
      <tstamps>35effd3a-84fe-4268-bade-3a4b727c5e22</tstamps>
    </comp>
    <comp ref="R2">
      <value>10</value>
      <footprint>Resistor_THT:R_Axial_DIN0204_L3.6mm_D1.6mm_P7.62mm_Horizontal</footprint>
      <libsource lib="Device" part="R" description="Resistor"/>
      <property name="Sheetname" value=""/>
      <property name="Sheetfile" value="ER-MIDI-CV4-02_DB.kicad_sch"/>
      <sheetpath names="/" tstamps="/"/>
      <tstamps>5b9ce758-067b-4a7e-a340-1168203c7fe8</tstamps>
    </comp>
    <comp ref="R3">
      <value>470</value>
      <footprint>Resistor_THT:R_Axial_DIN0204_L3.6mm_D1.6mm_P2.54mm_Vertical</footprint>
      <libsource lib="Device" part="R" description="Resistor"/>
      <property name="Sheetname" value=""/>
      <property name="Sheetfile" value="ER-MIDI-CV4-02_DB.kicad_sch"/>
      <sheetpath names="/" tstamps="/"/>
      <tstamps>76f2d397-8f3c-4799-a9c5-6ee7cbb8d293</tstamps>
    </comp>
    <comp ref="U1">
      <value>MCP4822-E/P</value>
      <footprint>Package_DIP:DIP-8_W7.62mm_Socket_LongPads</footprint>
      <libsource lib="Analog_DAC" part="MCP4822" description="2-Channel 12-Bit D/A Converters with SPI Interface and Internal Reference (2.048V)"/>
      <property name="Sheetname" value=""/>
      <property name="Sheetfile" value="ER-MIDI-CV4-02_DB.kicad_sch"/>
      <sheetpath names="/" tstamps="/"/>
      <tstamps>13c436f9-10bd-46a3-a92d-f3f9acb1c77f</tstamps>
    </comp>
    <comp ref="U2">
      <value>MCP4822-E/P</value>
      <footprint>Package_DIP:DIP-8_W7.62mm_Socket_LongPads</footprint>
      <libsource lib="Analog_DAC" part="MCP4822" description="2-Channel 12-Bit D/A Converters with SPI Interface and Internal Reference (2.048V)"/>
      <property name="Sheetname" value=""/>
      <property name="Sheetfile" value="ER-MIDI-CV4-02_DB.kicad_sch"/>
      <sheetpath names="/" tstamps="/"/>
      <tstamps>0ccd7e79-6c84-4a03-b47c-6d9d28cf07ba</tstamps>
    </comp>
    <comp ref="U3">
      <value>ARDUINO PRO MINI 5V</value>
      <footprint>LandBoards_BoardOutlines:ArduProMini</footprint>
      <libsource lib="VFO-003-rescue" part="ARDUPROMINI-ArduProMiniTKB" description=""/>
      <property name="Sheetname" value=""/>
      <property name="Sheetfile" value="ER-MIDI-CV4-02_DB.kicad_sch"/>
      <sheetpath names="/" tstamps="/"/>
      <tstamps>5d4ada07-162c-4372-b2f5-70e1608a509a</tstamps>
    </comp>
  </components>
  <libparts>
    <libpart lib="Analog_DAC" part="MCP4822">
      <description>2-Channel 12-Bit D/A Converters with SPI Interface and Internal Reference (2.048V)</description>
      <docs>http://ww1.microchip.com/downloads/en/DeviceDoc/20002249B.pdf</docs>
      <footprints>
        <fp>DIP*W7.62mm*</fp>
        <fp>SOIC*3.9x4.9mm*P1.27mm*</fp>
        <fp>MSOP*3x3mm*P0.65mm*</fp>
      </footprints>
      <fields>
        <field name="Reference">U</field>
        <field name="Value">MCP4822</field>
        <field name="Datasheet">http://ww1.microchip.com/downloads/en/DeviceDoc/20002249B.pdf</field>
      </fields>
      <pins>
        <pin num="1" name="Vdd" type="power_in"/>
        <pin num="2" name="~{CS}" type="input"/>
        <pin num="3" name="SCK" type="input"/>
        <pin num="4" name="SDI" type="input"/>
        <pin num="5" name="~{LDAC}" type="input"/>
        <pin num="6" name="VB" type="output"/>
        <pin num="7" name="Vss" type="power_in"/>
        <pin num="8" name="VA" type="output"/>
      </pins>
    </libpart>
    <libpart lib="Connector_Generic" part="Conn_01x02">
      <description>Generic connector, single row, 01x02, script generated (kicad-library-utils/schlib/autogen/connector/)</description>
      <docs>~</docs>
      <footprints>
        <fp>Connector*:*_1x??_*</fp>
      </footprints>
      <fields>
        <field name="Reference">J</field>
        <field name="Value">Conn_01x02</field>
        <field name="Datasheet">~</field>
      </fields>
      <pins>
        <pin num="1" name="Pin_1" type="passive"/>
        <pin num="2" name="Pin_2" type="passive"/>
      </pins>
    </libpart>
    <libpart lib="Connector_Generic" part="Conn_01x04">
      <description>Generic connector, single row, 01x04, script generated (kicad-library-utils/schlib/autogen/connector/)</description>
      <docs>~</docs>
      <footprints>
        <fp>Connector*:*_1x??_*</fp>
      </footprints>
      <fields>
        <field name="Reference">J</field>
        <field name="Value">Conn_01x04</field>
        <field name="Datasheet">~</field>
      </fields>
      <pins>
        <pin num="1" name="Pin_1" type="passive"/>
        <pin num="2" name="Pin_2" type="passive"/>
        <pin num="3" name="Pin_3" type="passive"/>
        <pin num="4" name="Pin_4" type="passive"/>
      </pins>
    </libpart>
    <libpart lib="Connector_Generic" part="Conn_01x10">
      <description>Generic connector, single row, 01x10, script generated (kicad-library-utils/schlib/autogen/connector/)</description>
      <docs>~</docs>
      <footprints>
        <fp>Connector*:*_1x??_*</fp>
      </footprints>
      <fields>
        <field name="Reference">J</field>
        <field name="Value">Conn_01x10</field>
        <field name="Datasheet">~</field>
      </fields>
      <pins>
        <pin num="1" name="Pin_1" type="passive"/>
        <pin num="2" name="Pin_2" type="passive"/>
        <pin num="3" name="Pin_3" type="passive"/>
        <pin num="4" name="Pin_4" type="passive"/>
        <pin num="5" name="Pin_5" type="passive"/>
        <pin num="6" name="Pin_6" type="passive"/>
        <pin num="7" name="Pin_7" type="passive"/>
        <pin num="8" name="Pin_8" type="passive"/>
        <pin num="9" name="Pin_9" type="passive"/>
        <pin num="10" name="Pin_10" type="passive"/>
      </pins>
    </libpart>
    <libpart lib="Connector_Generic" part="Conn_02x05_Odd_Even">
      <description>Generic connector, double row, 02x05, odd/even pin numbering scheme (row 1 odd numbers, row 2 even numbers), script generated (kicad-library-utils/schlib/autogen/connector/)</description>
      <docs>~</docs>
      <footprints>
        <fp>Connector*:*_2x??_*</fp>
      </footprints>
      <fields>
        <field name="Reference">J</field>
        <field name="Value">Conn_02x05_Odd_Even</field>
        <field name="Datasheet">~</field>
      </fields>
      <pins>
        <pin num="1" name="Pin_1" type="passive"/>
        <pin num="2" name="Pin_2" type="passive"/>
        <pin num="3" name="Pin_3" type="passive"/>
        <pin num="4" name="Pin_4" type="passive"/>
        <pin num="5" name="Pin_5" type="passive"/>
        <pin num="6" name="Pin_6" type="passive"/>
        <pin num="7" name="Pin_7" type="passive"/>
        <pin num="8" name="Pin_8" type="passive"/>
        <pin num="9" name="Pin_9" type="passive"/>
        <pin num="10" name="Pin_10" type="passive"/>
      </pins>
    </libpart>
    <libpart lib="Device" part="C">
      <description>Unpolarized capacitor</description>
      <docs>~</docs>
      <footprints>
        <fp>C_*</fp>
      </footprints>
      <fields>
        <field name="Reference">C</field>
        <field name="Value">C</field>
        <field name="Datasheet">~</field>
      </fields>
      <pins>
        <pin num="1" name="" type="passive"/>
        <pin num="2" name="" type="passive"/>
      </pins>
    </libpart>
    <libpart lib="Device" part="D_Schottky">
      <description>Schottky diode</description>
      <docs>~</docs>
      <footprints>
        <fp>TO-???*</fp>
        <fp>*_Diode_*</fp>
        <fp>*SingleDiode*</fp>
        <fp>D_*</fp>
      </footprints>
      <fields>
        <field name="Reference">D</field>
        <field name="Value">D_Schottky</field>
        <field name="Datasheet">~</field>
      </fields>
      <pins>
        <pin num="1" name="K" type="passive"/>
        <pin num="2" name="A" type="passive"/>
      </pins>
    </libpart>
    <libpart lib="Device" part="R">
      <description>Resistor</description>
      <docs>~</docs>
      <footprints>
        <fp>R_*</fp>
      </footprints>
      <fields>
        <field name="Reference">R</field>
        <field name="Value">R</field>
        <field name="Datasheet">~</field>
      </fields>
      <pins>
        <pin num="1" name="" type="passive"/>
        <pin num="2" name="" type="passive"/>
      </pins>
    </libpart>
    <libpart lib="LandBoards_Semis" part="DIODESCH-fixed">
      <footprints>
        <fp>D?</fp>
        <fp>S*</fp>
      </footprints>
      <fields>
        <field name="Reference">D</field>
        <field name="Value">DIODESCH-fixed</field>
      </fields>
      <pins>
        <pin num="1" name="K" type="passive"/>
        <pin num="2" name="A" type="passive"/>
      </pins>
    </libpart>
    <libpart lib="Transistor_BJT" part="2N3904">
      <description>0.2A Ic, 40V Vce, Small Signal NPN Transistor, TO-92</description>
      <docs>https://www.onsemi.com/pub/Collateral/2N3903-D.PDF</docs>
      <footprints>
        <fp>TO?92*</fp>
      </footprints>
      <fields>
        <field name="Reference">Q</field>
        <field name="Value">2N3904</field>
        <field name="Footprint">Package_TO_SOT_THT:TO-92_Inline</field>
        <field name="Datasheet">https://www.onsemi.com/pub/Collateral/2N3903-D.PDF</field>
      </fields>
      <pins>
        <pin num="1" name="E" type="passive"/>
        <pin num="2" name="B" type="passive"/>
        <pin num="3" name="C" type="passive"/>
      </pins>
    </libpart>
    <libpart lib="VFO-003-rescue" part="ARDUPROMINI-ArduProMiniTKB">
      <fields>
        <field name="Reference">uP</field>
        <field name="Value">ARDUPROMINI-ArduProMiniTKB</field>
      </fields>
      <pins>
        <pin num="1" name="GND" type="unspecified"/>
        <pin num="2" name="GND2" type="unspecified"/>
        <pin num="3" name="VccCBL" type="power_in"/>
        <pin num="4" name="RX1-CBL" type="unspecified"/>
        <pin num="5" name="TX0-CBL" type="unspecified"/>
        <pin num="6" name="DTR_I" type="unspecified"/>
        <pin num="7" name="TX0" type="bidirectional"/>
        <pin num="8" name="RX1" type="bidirectional"/>
        <pin num="9" name="RESET" type="input"/>
        <pin num="10" name="GND" type="unspecified"/>
        <pin num="11" name="D2" type="bidirectional"/>
        <pin num="12" name="D3" type="bidirectional"/>
        <pin num="13" name="D4" type="bidirectional"/>
        <pin num="14" name="D5" type="bidirectional"/>
        <pin num="15" name="D6" type="bidirectional"/>
        <pin num="16" name="D7" type="bidirectional"/>
        <pin num="17" name="D8" type="bidirectional"/>
        <pin num="18" name="D9" type="bidirectional"/>
        <pin num="19" name="RAW" type="unspecified"/>
        <pin num="20" name="GND3" type="unspecified"/>
        <pin num="21" name="RESET" type="input"/>
        <pin num="22" name="Vcc2" type="unspecified"/>
        <pin num="23" name="A3" type="bidirectional"/>
        <pin num="24" name="A2" type="bidirectional"/>
        <pin num="25" name="A1" type="bidirectional"/>
        <pin num="26" name="A0" type="bidirectional"/>
        <pin num="27" name="D13" type="bidirectional"/>
        <pin num="28" name="D12" type="input"/>
        <pin num="29" name="D11" type="bidirectional"/>
        <pin num="30" name="D10" type="bidirectional"/>
        <pin num="31" name="A5/SCL" type="bidirectional"/>
        <pin num="32" name="A4/SDA" type="bidirectional"/>
      </pins>
    </libpart>
  </libparts>
  <libraries>
    <library logical="Analog_DAC">
      <uri>C:\Program Files\KiCad\6.0\share\kicad\symbols\/Analog_DAC.kicad_sym</uri>
    </library>
    <library logical="Connector_Generic">
      <uri>C:\Program Files\KiCad\6.0\share\kicad\symbols\/Connector_Generic.kicad_sym</uri>
    </library>
    <library logical="Device">
      <uri>C:\Program Files\KiCad\6.0\share\kicad\symbols\/Device.kicad_sym</uri>
    </library>
    <library logical="LandBoards_Semis">
      <uri>C:/Users/HPz420/Documents/GitHub/land-boards/lb-boards/KiCAD/library/LandBoards_Semis.kicad_sym</uri>
    </library>
    <library logical="Transistor_BJT">
      <uri>C:\Program Files\KiCad\6.0\share\kicad\symbols\/Transistor_BJT.kicad_sym</uri>
    </library>
  </libraries>
  <nets>
    <net code="1" name="+5V">
      <node ref="C1" pin="1" pintype="passive"/>
      <node ref="C2" pin="1" pintype="passive"/>
      <node ref="C3" pin="1" pintype="passive"/>
      <node ref="D1" pin="1" pinfunction="K" pintype="passive"/>
      <node ref="D10" pin="1" pinfunction="K" pintype="passive"/>
      <node ref="D11" pin="1" pinfunction="K" pintype="passive"/>
      <node ref="D12" pin="1" pinfunction="K" pintype="passive"/>
      <node ref="D3" pin="1" pinfunction="K" pintype="passive"/>
      <node ref="D5" pin="1" pinfunction="K" pintype="passive"/>
      <node ref="J2" pin="1" pinfunction="Pin_1" pintype="passive"/>
      <node ref="J3" pin="3" pinfunction="Pin_3" pintype="passive"/>
      <node ref="J4" pin="1" pinfunction="Pin_1" pintype="passive"/>
      <node ref="R3" pin="2" pintype="passive"/>
      <node ref="U1" pin="1" pinfunction="Vdd" pintype="power_in"/>
      <node ref="U2" pin="1" pinfunction="Vdd" pintype="power_in"/>
      <node ref="U3" pin="22" pinfunction="Vcc2" pintype="unspecified"/>
    </net>
    <net code="2" name="+12P">
      <node ref="C4" pin="1" pintype="passive"/>
      <node ref="D13" pin="1" pinfunction="K" pintype="passive"/>
      <node ref="U3" pin="19" pinfunction="RAW" pintype="unspecified"/>
    </net>
    <net code="3" name="+12V">
      <node ref="J1" pin="10" pinfunction="Pin_10" pintype="passive"/>
      <node ref="J1" pin="9" pinfunction="Pin_9" pintype="passive"/>
      <node ref="R2" pin="1" pintype="passive"/>
    </net>
    <net code="4" name="/CLK">
      <node ref="D3" pin="2" pinfunction="A" pintype="passive"/>
      <node ref="D6" pin="1" pinfunction="K" pintype="passive"/>
      <node ref="J2" pin="8" pinfunction="Pin_8" pintype="passive"/>
      <node ref="U3" pin="13" pinfunction="D4" pintype="bidirectional"/>
    </net>
    <net code="5" name="/CV1_D">
      <node ref="D11" pin="2" pinfunction="A" pintype="passive"/>
      <node ref="D8" pin="1" pinfunction="K" pintype="passive"/>
      <node ref="J2" pin="6" pinfunction="Pin_6" pintype="passive"/>
      <node ref="U2" pin="8" pinfunction="VA" pintype="output"/>
    </net>
    <net code="6" name="/CV2_D">
      <node ref="D2" pin="1" pinfunction="K" pintype="passive"/>
      <node ref="D5" pin="2" pinfunction="A" pintype="passive"/>
      <node ref="J2" pin="4" pinfunction="Pin_4" pintype="passive"/>
      <node ref="U2" pin="6" pinfunction="VB" pintype="output"/>
    </net>
    <net code="7" name="/CV3_D">
      <node ref="D12" pin="2" pinfunction="A" pintype="passive"/>
      <node ref="D9" pin="1" pinfunction="K" pintype="passive"/>
      <node ref="J2" pin="7" pinfunction="Pin_7" pintype="passive"/>
      <node ref="U1" pin="8" pinfunction="VA" pintype="output"/>
    </net>
    <net code="8" name="/CV4_D">
      <node ref="D1" pin="2" pinfunction="A" pintype="passive"/>
      <node ref="D4" pin="1" pinfunction="K" pintype="passive"/>
      <node ref="J2" pin="3" pinfunction="Pin_3" pintype="passive"/>
      <node ref="U1" pin="6" pinfunction="VB" pintype="output"/>
    </net>
    <net code="9" name="/GATE">
      <node ref="D10" pin="2" pinfunction="A" pintype="passive"/>
      <node ref="D7" pin="1" pinfunction="K" pintype="passive"/>
      <node ref="J2" pin="2" pinfunction="Pin_2" pintype="passive"/>
      <node ref="U3" pin="14" pinfunction="D5" pintype="bidirectional"/>
    </net>
    <net code="10" name="/LDAC1*">
      <node ref="U2" pin="5" pinfunction="~{LDAC}" pintype="input"/>
      <node ref="U3" pin="18" pinfunction="D9" pintype="bidirectional"/>
    </net>
    <net code="11" name="/LDAC2*">
      <node ref="U1" pin="5" pinfunction="~{LDAC}" pintype="input"/>
      <node ref="U3" pin="17" pinfunction="D8" pintype="bidirectional"/>
    </net>
    <net code="12" name="/MOSI">
      <node ref="U1" pin="4" pinfunction="SDI" pintype="input"/>
      <node ref="U2" pin="4" pinfunction="SDI" pintype="input"/>
      <node ref="U3" pin="29" pinfunction="D11" pintype="bidirectional"/>
    </net>
    <net code="13" name="/OPTOUT-C">
      <node ref="J4" pin="3" pinfunction="Pin_3" pintype="passive"/>
      <node ref="J5" pin="1" pinfunction="Pin_1" pintype="passive"/>
    </net>
    <net code="14" name="/POT">
      <node ref="J2" pin="5" pinfunction="Pin_5" pintype="passive"/>
      <node ref="U3" pin="25" pinfunction="A1" pintype="bidirectional"/>
    </net>
    <net code="15" name="/RBI-C">
      <node ref="J4" pin="2" pinfunction="Pin_2" pintype="passive"/>
      <node ref="Q1" pin="3" pinfunction="C" pintype="passive"/>
      <node ref="R3" pin="1" pintype="passive"/>
    </net>
    <net code="16" name="/RBO">
      <node ref="Q1" pin="2" pinfunction="B" pintype="passive"/>
      <node ref="R1" pin="1" pintype="passive"/>
    </net>
    <net code="17" name="/SCK">
      <node ref="U1" pin="3" pinfunction="SCK" pintype="input"/>
      <node ref="U2" pin="3" pinfunction="SCK" pintype="input"/>
      <node ref="U3" pin="27" pinfunction="D13" pintype="bidirectional"/>
    </net>
    <net code="18" name="/SCL">
      <node ref="J3" pin="1" pinfunction="Pin_1" pintype="passive"/>
      <node ref="U3" pin="31" pinfunction="A5/SCL" pintype="bidirectional"/>
    </net>
    <net code="19" name="/SDA">
      <node ref="J3" pin="2" pinfunction="Pin_2" pintype="passive"/>
      <node ref="U3" pin="32" pinfunction="A4/SDA" pintype="bidirectional"/>
    </net>
    <net code="20" name="/SS">
      <node ref="U1" pin="2" pinfunction="~{CS}" pintype="input"/>
      <node ref="U2" pin="2" pinfunction="~{CS}" pintype="input"/>
      <node ref="U3" pin="30" pinfunction="D10" pintype="bidirectional"/>
    </net>
    <net code="21" name="/TXD">
      <node ref="R1" pin="2" pintype="passive"/>
      <node ref="U3" pin="7" pinfunction="TX0" pintype="bidirectional"/>
    </net>
    <net code="22" name="GND">
      <node ref="C1" pin="2" pintype="passive"/>
      <node ref="C2" pin="2" pintype="passive"/>
      <node ref="C3" pin="2" pintype="passive"/>
      <node ref="C4" pin="2" pintype="passive"/>
      <node ref="D2" pin="2" pinfunction="A" pintype="passive"/>
      <node ref="D4" pin="2" pinfunction="A" pintype="passive"/>
      <node ref="D6" pin="2" pinfunction="A" pintype="passive"/>
      <node ref="D7" pin="2" pinfunction="A" pintype="passive"/>
      <node ref="D8" pin="2" pinfunction="A" pintype="passive"/>
      <node ref="D9" pin="2" pinfunction="A" pintype="passive"/>
      <node ref="J1" pin="3" pinfunction="Pin_3" pintype="passive"/>
      <node ref="J1" pin="4" pinfunction="Pin_4" pintype="passive"/>
      <node ref="J1" pin="5" pinfunction="Pin_5" pintype="passive"/>
      <node ref="J1" pin="6" pinfunction="Pin_6" pintype="passive"/>
      <node ref="J1" pin="7" pinfunction="Pin_7" pintype="passive"/>
      <node ref="J1" pin="8" pinfunction="Pin_8" pintype="passive"/>
      <node ref="J2" pin="10" pinfunction="Pin_10" pintype="passive"/>
      <node ref="J3" pin="4" pinfunction="Pin_4" pintype="passive"/>
      <node ref="J4" pin="4" pinfunction="Pin_4" pintype="passive"/>
      <node ref="Q1" pin="1" pinfunction="E" pintype="passive"/>
      <node ref="U1" pin="7" pinfunction="Vss" pintype="power_in"/>
      <node ref="U2" pin="7" pinfunction="Vss" pintype="power_in"/>
      <node ref="U3" pin="1" pinfunction="GND" pintype="unspecified"/>
      <node ref="U3" pin="10" pinfunction="GND" pintype="unspecified"/>
      <node ref="U3" pin="2" pinfunction="GND2" pintype="unspecified"/>
      <node ref="U3" pin="20" pinfunction="GND3" pintype="unspecified"/>
    </net>
    <net code="23" name="Net-(D13-Pad2)">
      <node ref="D13" pin="2" pinfunction="A" pintype="passive"/>
      <node ref="R2" pin="2" pintype="passive"/>
    </net>
    <net code="24" name="Net-(J5-Pad2)">
      <node ref="J5" pin="2" pinfunction="Pin_2" pintype="passive"/>
      <node ref="U3" pin="8" pinfunction="RX1" pintype="bidirectional"/>
    </net>
    <net code="25" name="unconnected-(J1-Pad1)">
      <node ref="J1" pin="1" pinfunction="Pin_1" pintype="passive"/>
    </net>
    <net code="26" name="unconnected-(J1-Pad2)">
      <node ref="J1" pin="2" pinfunction="Pin_2" pintype="passive"/>
    </net>
    <net code="27" name="unconnected-(J2-Pad9)">
      <node ref="J2" pin="9" pinfunction="Pin_9" pintype="passive"/>
    </net>
    <net code="28" name="unconnected-(U3-Pad3)">
      <node ref="U3" pin="3" pinfunction="VccCBL" pintype="power_in"/>
    </net>
    <net code="29" name="unconnected-(U3-Pad4)">
      <node ref="U3" pin="4" pinfunction="RX1-CBL" pintype="unspecified"/>
    </net>
    <net code="30" name="unconnected-(U3-Pad5)">
      <node ref="U3" pin="5" pinfunction="TX0-CBL" pintype="unspecified"/>
    </net>
    <net code="31" name="unconnected-(U3-Pad6)">
      <node ref="U3" pin="6" pinfunction="DTR_I" pintype="unspecified"/>
    </net>
    <net code="32" name="unconnected-(U3-Pad9)">
      <node ref="U3" pin="9" pinfunction="RESET" pintype="input+no_connect"/>
    </net>
    <net code="33" name="unconnected-(U3-Pad11)">
      <node ref="U3" pin="11" pinfunction="D2" pintype="bidirectional+no_connect"/>
    </net>
    <net code="34" name="unconnected-(U3-Pad12)">
      <node ref="U3" pin="12" pinfunction="D3" pintype="bidirectional+no_connect"/>
    </net>
    <net code="35" name="unconnected-(U3-Pad15)">
      <node ref="U3" pin="15" pinfunction="D6" pintype="bidirectional+no_connect"/>
    </net>
    <net code="36" name="unconnected-(U3-Pad16)">
      <node ref="U3" pin="16" pinfunction="D7" pintype="bidirectional+no_connect"/>
    </net>
    <net code="37" name="unconnected-(U3-Pad21)">
      <node ref="U3" pin="21" pinfunction="RESET" pintype="input+no_connect"/>
    </net>
    <net code="38" name="unconnected-(U3-Pad23)">
      <node ref="U3" pin="23" pinfunction="A3" pintype="bidirectional+no_connect"/>
    </net>
    <net code="39" name="unconnected-(U3-Pad24)">
      <node ref="U3" pin="24" pinfunction="A2" pintype="bidirectional+no_connect"/>
    </net>
    <net code="40" name="unconnected-(U3-Pad26)">
      <node ref="U3" pin="26" pinfunction="A0" pintype="bidirectional+no_connect"/>
    </net>
    <net code="41" name="unconnected-(U3-Pad28)">
      <node ref="U3" pin="28" pinfunction="D12" pintype="input+no_connect"/>
    </net>
  </nets>
</export>
