<?xml version="1.0" encoding="UTF-8"?>
<export version="E">
  <design>
    <source>C:\Users\HPz420\Documents\GitHub\land-boards\lb-boards\RetroCPUs\SIMPLE-68008\SIMPLE-68008.kicad_sch</source>
    <date>9/17/2022 12:41:42 PM</date>
    <tool>Eeschema (6.0.1)</tool>
    <sheet number="1" name="/" tstamps="/">
      <title_block>
        <title>SIMPLE-68008</title>
        <company>Land Boards LLC</company>
        <rev>1</rev>
        <date>2022-09-16</date>
        <source>SIMPLE-68008.kicad_sch</source>
        <comment number="1" value=""/>
        <comment number="2" value=""/>
        <comment number="3" value=""/>
        <comment number="4" value=""/>
        <comment number="5" value=""/>
        <comment number="6" value=""/>
        <comment number="7" value=""/>
        <comment number="8" value=""/>
        <comment number="9" value=""/>
      </title_block>
    </sheet>
  </design>
  <components>
    <comp ref="C1">
      <value>0.1uF</value>
      <footprint>Capacitor_THT:C_Rect_L4.0mm_W2.5mm_P2.50mm</footprint>
      <libsource lib="Device" part="C_Small" description="Unpolarized capacitor, small symbol"/>
      <property name="Sheetname" value=""/>
      <property name="Sheetfile" value="SIMPLE-68008.kicad_sch"/>
      <sheetpath names="/" tstamps="/"/>
      <tstamps>ef90b208-0d39-4941-8153-3950cb4d44a6</tstamps>
    </comp>
    <comp ref="C2">
      <value>0.1uF</value>
      <footprint>Capacitor_THT:C_Rect_L4.0mm_W2.5mm_P2.50mm</footprint>
      <libsource lib="Device" part="C_Small" description="Unpolarized capacitor, small symbol"/>
      <property name="Sheetname" value=""/>
      <property name="Sheetfile" value="SIMPLE-68008.kicad_sch"/>
      <sheetpath names="/" tstamps="/"/>
      <tstamps>903bc584-0c03-4714-baaf-322216b1b552</tstamps>
    </comp>
    <comp ref="C3">
      <value>0.1uF</value>
      <footprint>Capacitor_THT:C_Rect_L4.0mm_W2.5mm_P2.50mm</footprint>
      <libsource lib="Device" part="C_Small" description="Unpolarized capacitor, small symbol"/>
      <property name="Sheetname" value=""/>
      <property name="Sheetfile" value="SIMPLE-68008.kicad_sch"/>
      <sheetpath names="/" tstamps="/"/>
      <tstamps>1b0dd7ad-be0a-4c06-921b-c5ce370a7e6e</tstamps>
    </comp>
    <comp ref="C4">
      <value>0.1uF</value>
      <footprint>Capacitor_THT:C_Rect_L4.0mm_W2.5mm_P2.50mm</footprint>
      <libsource lib="Device" part="C_Small" description="Unpolarized capacitor, small symbol"/>
      <property name="Sheetname" value=""/>
      <property name="Sheetfile" value="SIMPLE-68008.kicad_sch"/>
      <sheetpath names="/" tstamps="/"/>
      <tstamps>a0821229-6cb9-45c7-b489-2c40da67ae0b</tstamps>
    </comp>
    <comp ref="C5">
      <value>0.1uF</value>
      <footprint>Capacitor_THT:C_Rect_L4.0mm_W2.5mm_P2.50mm</footprint>
      <libsource lib="Device" part="C_Small" description="Unpolarized capacitor, small symbol"/>
      <property name="Sheetname" value=""/>
      <property name="Sheetfile" value="SIMPLE-68008.kicad_sch"/>
      <sheetpath names="/" tstamps="/"/>
      <tstamps>1d83d804-94c4-46b6-97cb-3e9e58c79eeb</tstamps>
    </comp>
    <comp ref="C6">
      <value>0.1uF</value>
      <footprint>Capacitor_THT:C_Rect_L4.0mm_W2.5mm_P2.50mm</footprint>
      <libsource lib="Device" part="C_Small" description="Unpolarized capacitor, small symbol"/>
      <property name="Sheetname" value=""/>
      <property name="Sheetfile" value="SIMPLE-68008.kicad_sch"/>
      <sheetpath names="/" tstamps="/"/>
      <tstamps>6ce15403-2b21-4a31-9dc0-be708f96ec89</tstamps>
    </comp>
    <comp ref="C7">
      <value>0-5pf</value>
      <footprint>Capacitor_THT:C_Rect_L4.0mm_W2.5mm_P2.50mm</footprint>
      <libsource lib="Device" part="C_Small" description="Unpolarized capacitor, small symbol"/>
      <property name="Sheetname" value=""/>
      <property name="Sheetfile" value="SIMPLE-68008.kicad_sch"/>
      <sheetpath names="/" tstamps="/"/>
      <tstamps>0be51d7a-bbb3-4da3-9db3-a7acea6cd981</tstamps>
    </comp>
    <comp ref="C8">
      <value>10-15pF</value>
      <footprint>Capacitor_THT:C_Rect_L4.0mm_W2.5mm_P2.50mm</footprint>
      <libsource lib="Device" part="C_Small" description="Unpolarized capacitor, small symbol"/>
      <property name="Sheetname" value=""/>
      <property name="Sheetfile" value="SIMPLE-68008.kicad_sch"/>
      <sheetpath names="/" tstamps="/"/>
      <tstamps>a462bfb9-c47e-401c-8a7b-961872203282</tstamps>
    </comp>
    <comp ref="C9">
      <value>0.1uF</value>
      <footprint>Capacitor_THT:C_Rect_L4.0mm_W2.5mm_P2.50mm</footprint>
      <libsource lib="Device" part="C_Small" description="Unpolarized capacitor, small symbol"/>
      <property name="Sheetname" value=""/>
      <property name="Sheetfile" value="SIMPLE-68008.kicad_sch"/>
      <sheetpath names="/" tstamps="/"/>
      <tstamps>8c46d8bb-7bb6-4976-b9ed-53880728657a</tstamps>
    </comp>
    <comp ref="H1">
      <value>HEADER, STRT, 2X4</value>
      <footprint>Connector_PinHeader_2.54mm:PinHeader_2x04_P2.54mm_Vertical</footprint>
      <libsource lib="Connector_Generic" part="Conn_02x04_Odd_Even" description="Generic connector, double row, 02x04, odd/even pin numbering scheme (row 1 odd numbers, row 2 even numbers), script generated (kicad-library-utils/schlib/autogen/connector/)"/>
      <property name="Sheetname" value=""/>
      <property name="Sheetfile" value="SIMPLE-68008.kicad_sch"/>
      <sheetpath names="/" tstamps="/"/>
      <tstamps>32ab811e-a79b-4e00-ad6a-f97e15009684</tstamps>
    </comp>
    <comp ref="H2">
      <value>JUMPER (1X3)</value>
      <footprint>Connector_PinHeader_2.54mm:PinHeader_1x03_P2.54mm_Vertical</footprint>
      <libsource lib="Connector_Generic" part="Conn_01x03" description="Generic connector, single row, 01x03, script generated (kicad-library-utils/schlib/autogen/connector/)"/>
      <property name="Sheetname" value=""/>
      <property name="Sheetfile" value="SIMPLE-68008.kicad_sch"/>
      <sheetpath names="/" tstamps="/"/>
      <tstamps>d2e2c2a9-253a-4b2b-b8e3-e1c5ea98a776</tstamps>
    </comp>
    <comp ref="H3">
      <value>JUMPER (1X3)</value>
      <footprint>Connector_PinHeader_2.54mm:PinHeader_1x03_P2.54mm_Vertical</footprint>
      <libsource lib="Connector_Generic" part="Conn_01x03" description="Generic connector, single row, 01x03, script generated (kicad-library-utils/schlib/autogen/connector/)"/>
      <property name="Sheetname" value=""/>
      <property name="Sheetfile" value="SIMPLE-68008.kicad_sch"/>
      <sheetpath names="/" tstamps="/"/>
      <tstamps>6c79a9cd-fb14-4078-8d39-42e5a14de4d2</tstamps>
    </comp>
    <comp ref="H4">
      <value>JUMPER (1X3)</value>
      <footprint>Connector_PinHeader_2.54mm:PinHeader_1x03_P2.54mm_Vertical</footprint>
      <libsource lib="Connector_Generic" part="Conn_01x03" description="Generic connector, single row, 01x03, script generated (kicad-library-utils/schlib/autogen/connector/)"/>
      <property name="Sheetname" value=""/>
      <property name="Sheetfile" value="SIMPLE-68008.kicad_sch"/>
      <sheetpath names="/" tstamps="/"/>
      <tstamps>d9692ec8-7293-4c12-8f18-6f0c271c7278</tstamps>
    </comp>
    <comp ref="H5">
      <value>JUMPER (1X3)</value>
      <footprint>Connector_PinHeader_2.54mm:PinHeader_1x03_P2.54mm_Vertical</footprint>
      <libsource lib="Connector_Generic" part="Conn_01x03" description="Generic connector, single row, 01x03, script generated (kicad-library-utils/schlib/autogen/connector/)"/>
      <property name="Sheetname" value=""/>
      <property name="Sheetfile" value="SIMPLE-68008.kicad_sch"/>
      <sheetpath names="/" tstamps="/"/>
      <tstamps>d609a210-afc7-45f7-98a3-80e0886b01c2</tstamps>
    </comp>
    <comp ref="H6">
      <value>JUMPER (1X3)</value>
      <footprint>Connector_PinHeader_2.54mm:PinHeader_1x03_P2.54mm_Vertical</footprint>
      <libsource lib="Connector_Generic" part="Conn_01x03" description="Generic connector, single row, 01x03, script generated (kicad-library-utils/schlib/autogen/connector/)"/>
      <property name="Sheetname" value=""/>
      <property name="Sheetfile" value="SIMPLE-68008.kicad_sch"/>
      <sheetpath names="/" tstamps="/"/>
      <tstamps>85572aaa-69e1-42b5-9e1d-b473ffeba69a</tstamps>
    </comp>
    <comp ref="J1">
      <value>Conn_02x06_Odd_Even</value>
      <footprint>Connector_PinHeader_2.54mm:PinHeader_2x06_P2.54mm_Vertical</footprint>
      <libsource lib="Connector_Generic" part="Conn_02x06_Odd_Even" description="Generic connector, double row, 02x06, odd/even pin numbering scheme (row 1 odd numbers, row 2 even numbers), script generated (kicad-library-utils/schlib/autogen/connector/)"/>
      <property name="Sheetname" value=""/>
      <property name="Sheetfile" value="SIMPLE-68008.kicad_sch"/>
      <sheetpath names="/" tstamps="/"/>
      <tstamps>5179b4c0-d605-49a9-8e55-33c1e05f1906</tstamps>
    </comp>
    <comp ref="J2">
      <value>Conn_01x06</value>
      <footprint>Connector_PinHeader_2.54mm:PinHeader_1x06_P2.54mm_Vertical</footprint>
      <libsource lib="Connector_Generic" part="Conn_01x06" description="Generic connector, single row, 01x06, script generated (kicad-library-utils/schlib/autogen/connector/)"/>
      <property name="Sheetname" value=""/>
      <property name="Sheetfile" value="SIMPLE-68008.kicad_sch"/>
      <sheetpath names="/" tstamps="/"/>
      <tstamps>30266682-3d9c-4ce9-a77c-1001ec1220df</tstamps>
    </comp>
    <comp ref="J3">
      <value>Conn_01x08</value>
      <footprint>Connector_PinHeader_2.54mm:PinHeader_1x08_P2.54mm_Vertical</footprint>
      <libsource lib="Connector_Generic" part="Conn_01x08" description="Generic connector, single row, 01x08, script generated (kicad-library-utils/schlib/autogen/connector/)"/>
      <property name="Sheetname" value=""/>
      <property name="Sheetfile" value="SIMPLE-68008.kicad_sch"/>
      <sheetpath names="/" tstamps="/"/>
      <tstamps>2663d143-b1a1-4765-aa0f-6cb037e68167</tstamps>
    </comp>
    <comp ref="MTG1">
      <value>MTG_HOLE</value>
      <footprint>LandBoards_MountHoles:MTG-6-32</footprint>
      <libsource lib="LandBoards" part="MTG_HOLE" description=""/>
      <property name="Sheetname" value=""/>
      <property name="Sheetfile" value="SIMPLE-68008.kicad_sch"/>
      <sheetpath names="/" tstamps="/"/>
      <tstamps>c6801334-1a47-43c3-835d-d452425f2cb0</tstamps>
    </comp>
    <comp ref="MTG2">
      <value>MTG_HOLE</value>
      <footprint>LandBoards_MountHoles:MTG-6-32</footprint>
      <libsource lib="LandBoards" part="MTG_HOLE" description=""/>
      <property name="Sheetname" value=""/>
      <property name="Sheetfile" value="SIMPLE-68008.kicad_sch"/>
      <sheetpath names="/" tstamps="/"/>
      <tstamps>b484bba9-6b6e-4c2b-9de6-d397b86297af</tstamps>
    </comp>
    <comp ref="MTG3">
      <value>MTG_HOLE</value>
      <footprint>LandBoards_MountHoles:MTG-6-32</footprint>
      <libsource lib="LandBoards" part="MTG_HOLE" description=""/>
      <property name="Sheetname" value=""/>
      <property name="Sheetfile" value="SIMPLE-68008.kicad_sch"/>
      <sheetpath names="/" tstamps="/"/>
      <tstamps>f3044919-d619-4023-a077-31fbca3f5f56</tstamps>
    </comp>
    <comp ref="MTG4">
      <value>MTG_HOLE</value>
      <footprint>LandBoards_MountHoles:MTG-6-32</footprint>
      <libsource lib="LandBoards" part="MTG_HOLE" description=""/>
      <property name="Sheetname" value=""/>
      <property name="Sheetfile" value="SIMPLE-68008.kicad_sch"/>
      <sheetpath names="/" tstamps="/"/>
      <tstamps>86003abc-61e1-4185-984b-d34b1fe814aa</tstamps>
    </comp>
    <comp ref="R1">
      <value>2.7K</value>
      <footprint>Resistor_THT:R_Axial_DIN0204_L3.6mm_D1.6mm_P7.62mm_Horizontal</footprint>
      <datasheet>https://www.mouser.com/ProductDetail/Xicon/299-2.7K-RC?qs=sGAEpiMZZMsPqMdJzcrNwi5wZazroUaaviDzz9InDsw%3D</datasheet>
      <libsource lib="Device" part="R" description="Resistor"/>
      <property name="Sheetname" value=""/>
      <property name="Sheetfile" value="SIMPLE-68008.kicad_sch"/>
      <sheetpath names="/" tstamps="/"/>
      <tstamps>c4647333-aad2-40e6-a8b2-489397d4cf19</tstamps>
    </comp>
    <comp ref="R2">
      <value>2.7K</value>
      <footprint>Resistor_THT:R_Axial_DIN0204_L3.6mm_D1.6mm_P7.62mm_Horizontal</footprint>
      <datasheet>https://www.mouser.com/ProductDetail/Xicon/299-2.7K-RC?qs=sGAEpiMZZMsPqMdJzcrNwi5wZazroUaaviDzz9InDsw%3D</datasheet>
      <libsource lib="Device" part="R" description="Resistor"/>
      <property name="Sheetname" value=""/>
      <property name="Sheetfile" value="SIMPLE-68008.kicad_sch"/>
      <sheetpath names="/" tstamps="/"/>
      <tstamps>27c92c05-6595-482f-af5c-746aea1d950e</tstamps>
    </comp>
    <comp ref="R3">
      <value>2.7K</value>
      <footprint>Resistor_THT:R_Axial_DIN0204_L3.6mm_D1.6mm_P7.62mm_Horizontal</footprint>
      <datasheet>https://www.mouser.com/ProductDetail/Xicon/299-2.7K-RC?qs=sGAEpiMZZMsPqMdJzcrNwi5wZazroUaaviDzz9InDsw%3D</datasheet>
      <libsource lib="Device" part="R" description="Resistor"/>
      <property name="Sheetname" value=""/>
      <property name="Sheetfile" value="SIMPLE-68008.kicad_sch"/>
      <sheetpath names="/" tstamps="/"/>
      <tstamps>724d47bd-0f8e-4032-a3f1-7934d8e34797</tstamps>
    </comp>
    <comp ref="R4">
      <value>2.7K</value>
      <footprint>Resistor_THT:R_Axial_DIN0204_L3.6mm_D1.6mm_P7.62mm_Horizontal</footprint>
      <datasheet>https://www.mouser.com/ProductDetail/Xicon/299-2.7K-RC?qs=sGAEpiMZZMsPqMdJzcrNwi5wZazroUaaviDzz9InDsw%3D</datasheet>
      <libsource lib="Device" part="R" description="Resistor"/>
      <property name="Sheetname" value=""/>
      <property name="Sheetfile" value="SIMPLE-68008.kicad_sch"/>
      <sheetpath names="/" tstamps="/"/>
      <tstamps>fd610f15-3810-4594-94ce-06da37e3eade</tstamps>
    </comp>
    <comp ref="R5">
      <value>2.7K</value>
      <footprint>Resistor_THT:R_Axial_DIN0204_L3.6mm_D1.6mm_P7.62mm_Horizontal</footprint>
      <datasheet>https://www.mouser.com/ProductDetail/Xicon/299-2.7K-RC?qs=sGAEpiMZZMsPqMdJzcrNwi5wZazroUaaviDzz9InDsw%3D</datasheet>
      <libsource lib="Device" part="R" description="Resistor"/>
      <property name="Sheetname" value=""/>
      <property name="Sheetfile" value="SIMPLE-68008.kicad_sch"/>
      <sheetpath names="/" tstamps="/"/>
      <tstamps>ec268f18-ae47-4c42-9dd3-72a6281534d8</tstamps>
    </comp>
    <comp ref="R6">
      <value>2.7K</value>
      <footprint>Resistor_THT:R_Axial_DIN0204_L3.6mm_D1.6mm_P7.62mm_Horizontal</footprint>
      <datasheet>https://www.mouser.com/ProductDetail/Xicon/299-2.7K-RC?qs=sGAEpiMZZMsPqMdJzcrNwi5wZazroUaaviDzz9InDsw%3D</datasheet>
      <libsource lib="Device" part="R" description="Resistor"/>
      <property name="Sheetname" value=""/>
      <property name="Sheetfile" value="SIMPLE-68008.kicad_sch"/>
      <sheetpath names="/" tstamps="/"/>
      <tstamps>d9eb6982-3c87-421b-a571-d1b545f097db</tstamps>
    </comp>
    <comp ref="SW1">
      <value>PUSHBUTTON, 6MM</value>
      <footprint>Button_Switch_THT:SW_PUSH_6mm_H8.5mm</footprint>
      <libsource lib="Switch" part="SW_Push" description="Push button switch, generic, two pins"/>
      <property name="Sheetname" value=""/>
      <property name="Sheetfile" value="SIMPLE-68008.kicad_sch"/>
      <sheetpath names="/" tstamps="/"/>
      <tstamps>0878a2af-dfcb-458c-b62f-0ced983b14da</tstamps>
    </comp>
    <comp ref="U1">
      <value>10 MHz</value>
      <footprint>Oscillator:Oscillator_DIP-14_LargePads</footprint>
      <libsource lib="LandBoards_Semis" part="OSC" description=""/>
      <property name="Sheetname" value=""/>
      <property name="Sheetfile" value="SIMPLE-68008.kicad_sch"/>
      <sheetpath names="/" tstamps="/"/>
      <tstamps>36131634-c3ac-4133-a779-a13125d5274d</tstamps>
    </comp>
    <comp ref="U2">
      <value>GAL16V8</value>
      <footprint>Package_DIP:DIP-20_W7.62mm_Socket_LongPads</footprint>
      <libsource lib="Logic_Programmable" part="GAL16V8" description="Programmable Logic Array, DIP-20/SOIC-20/PLCC-20"/>
      <property name="Sheetname" value=""/>
      <property name="Sheetfile" value="SIMPLE-68008.kicad_sch"/>
      <sheetpath names="/" tstamps="/"/>
      <tstamps>fb7c2316-3825-4403-8132-8f1450ea7c1c</tstamps>
    </comp>
    <comp ref="U3">
      <value>GAL16V8</value>
      <footprint>Package_DIP:DIP-20_W7.62mm_Socket_LongPads</footprint>
      <libsource lib="Logic_Programmable" part="GAL16V8" description="Programmable Logic Array, DIP-20/SOIC-20/PLCC-20"/>
      <property name="Sheetname" value=""/>
      <property name="Sheetfile" value="SIMPLE-68008.kicad_sch"/>
      <sheetpath names="/" tstamps="/"/>
      <tstamps>130813d5-257a-40bd-a9d3-208fcce868d8</tstamps>
    </comp>
    <comp ref="U4">
      <value>DS1813-5 (OPT)</value>
      <footprint>Package_TO_SOT_THT:TO-92</footprint>
      <datasheet>https://www.mouser.com/c/?q=DS1813-5</datasheet>
      <libsource lib="Connector_Generic" part="Conn_01x03" description="Generic connector, single row, 01x03, script generated (kicad-library-utils/schlib/autogen/connector/)"/>
      <property name="Sheetname" value=""/>
      <property name="Sheetfile" value="SIMPLE-68008.kicad_sch"/>
      <sheetpath names="/" tstamps="/"/>
      <tstamps>dc6d1a36-83fd-4a58-a444-ed7a1aebe79a</tstamps>
    </comp>
    <comp ref="U5">
      <value>MC68008D-10</value>
      <footprint>Package_DIP:DIP-48_W15.24mm_LongPads</footprint>
      <datasheet>https://www.nxp.com/docs/en/reference-manual/MC68000UM.pdf</datasheet>
      <libsource lib="CPU_NXP_68000" part="68008D" description="16/32-bit Microprocessor, 8-bit databus"/>
      <property name="Sheetname" value=""/>
      <property name="Sheetfile" value="SIMPLE-68008.kicad_sch"/>
      <sheetpath names="/" tstamps="/"/>
      <tstamps>911aa946-11a4-4082-a79a-bc4f1c265350</tstamps>
    </comp>
    <comp ref="U6">
      <value>68681</value>
      <footprint>Package_DIP:DIP-40_W15.24mm_LongPads</footprint>
      <libsource lib="LandBoards_Semis" part="68681" description="Interface serie 2 voies + 1 port parallele"/>
      <property name="Sheetname" value=""/>
      <property name="Sheetfile" value="SIMPLE-68008.kicad_sch"/>
      <sheetpath names="/" tstamps="/"/>
      <tstamps>dad0c3c6-901b-4e18-905b-596da84ad296</tstamps>
    </comp>
    <comp ref="U7">
      <value>AS6C4008-55PCN</value>
      <footprint>Package_DIP:DIP-32_W15.24mm</footprint>
      <datasheet>https://www.alliancememory.com/wp-content/uploads/pdf/AS6C4008.pdf</datasheet>
      <libsource lib="Memory_RAM" part="AS6C4008-55PCN" description="512K x 8 Low Power CMOS RAM, DIP-32"/>
      <property name="Sheetname" value=""/>
      <property name="Sheetfile" value="SIMPLE-68008.kicad_sch"/>
      <sheetpath names="/" tstamps="/"/>
      <tstamps>7063909c-2e6b-47dc-8258-7530e50f789e</tstamps>
    </comp>
    <comp ref="U8">
      <value>27C040</value>
      <footprint>Package_DIP:DIP-32_W15.24mm_LongPads</footprint>
      <datasheet>http://ww1.microchip.com/downloads/en/devicedoc/doc0189.pdf</datasheet>
      <libsource lib="Memory_EPROM" part="27C040" description="OTP EPROM 4 MiBit (512 Ki x 8)"/>
      <property name="Sheetname" value=""/>
      <property name="Sheetfile" value="SIMPLE-68008.kicad_sch"/>
      <sheetpath names="/" tstamps="/"/>
      <tstamps>56e4b6f8-1124-445f-9e4a-f6e2c71ab1b0</tstamps>
    </comp>
    <comp ref="U90">
      <value>27C020</value>
      <footprint>Package_DIP:DIP-32_W15.24mm_LongPads</footprint>
      <datasheet>http://ww1.microchip.com/downloads/en/devicedoc/doc0570.pdf</datasheet>
      <libsource lib="Memory_EPROM" part="27C020" description="OTP EPROM 2 MiBit (256 Ki x 8 Bit)"/>
      <property name="Sheetname" value=""/>
      <property name="Sheetfile" value="SIMPLE-68008.kicad_sch"/>
      <property name="exclude_from_board"/>
      <sheetpath names="/" tstamps="/"/>
      <tstamps>e34f5459-0c89-4a11-b588-d7e3bc0928d1</tstamps>
    </comp>
    <comp ref="U91">
      <value>27C010</value>
      <datasheet>http://ww1.microchip.com/downloads/en/DeviceDoc/doc0321.pdf</datasheet>
      <libsource lib="Memory_EPROM" part="27C010" description="OTP EPROM 1 MiBit (128 Ki x 8 Bit)"/>
      <property name="Sheetname" value=""/>
      <property name="Sheetfile" value="SIMPLE-68008.kicad_sch"/>
      <property name="exclude_from_board"/>
      <sheetpath names="/" tstamps="/"/>
      <tstamps>a041fd1c-7628-45d3-bf8e-41ee69b7c3fa</tstamps>
    </comp>
    <comp ref="U92">
      <value>27C512</value>
      <footprint>Package_DIP:DIP-28_W15.24mm</footprint>
      <datasheet>http://ww1.microchip.com/downloads/en/DeviceDoc/doc0015.pdf</datasheet>
      <libsource lib="Memory_EPROM" part="27C512" description="OTP EPROM 512 KiBit"/>
      <property name="Sheetname" value=""/>
      <property name="Sheetfile" value="SIMPLE-68008.kicad_sch"/>
      <property name="exclude_from_board"/>
      <sheetpath names="/" tstamps="/"/>
      <tstamps>0d6471e8-d8ba-470b-bedb-44e4531df7c3</tstamps>
    </comp>
    <comp ref="U93">
      <value>27C256</value>
      <footprint>Package_DIP:DIP-28_W15.24mm</footprint>
      <datasheet>http://ww1.microchip.com/downloads/en/DeviceDoc/doc0014.pdf</datasheet>
      <libsource lib="Memory_EPROM" part="27C256" description="OTP EPROM 256 KiBit"/>
      <property name="Sheetname" value=""/>
      <property name="Sheetfile" value="SIMPLE-68008.kicad_sch"/>
      <property name="exclude_from_board"/>
      <sheetpath names="/" tstamps="/"/>
      <tstamps>4b43e648-34db-4d79-9365-e9680699c0e0</tstamps>
    </comp>
    <comp ref="U94">
      <value>27C128</value>
      <footprint>Package_DIP:DIP-28_W15.24mm</footprint>
      <datasheet>http://ww1.microchip.com/downloads/en/devicedoc/11003L.pdf</datasheet>
      <libsource lib="Memory_EPROM" part="27C128" description="OTP EPROM 128 KiBit, [Obsolete 2004-01]"/>
      <property name="Sheetname" value=""/>
      <property name="Sheetfile" value="SIMPLE-68008.kicad_sch"/>
      <property name="exclude_from_board"/>
      <sheetpath names="/" tstamps="/"/>
      <tstamps>e2ec0302-bac5-4db7-b9a9-5298330646db</tstamps>
    </comp>
    <comp ref="U95">
      <value>27C64</value>
      <footprint>Package_DIP:DIP-28_W15.24mm</footprint>
      <datasheet>http://ww1.microchip.com/downloads/en/DeviceDoc/11107M.pdf</datasheet>
      <libsource lib="Memory_EPROM" part="27C64" description="OTP EPROM 64 KiBit, [Obsolete 2004-01]"/>
      <property name="Sheetname" value=""/>
      <property name="Sheetfile" value="SIMPLE-68008.kicad_sch"/>
      <property name="exclude_from_board"/>
      <sheetpath names="/" tstamps="/"/>
      <tstamps>0aee3321-da98-49e9-8ef3-7a2a07fadb35</tstamps>
    </comp>
    <comp ref="Y1">
      <value>3.6864 MHz</value>
      <footprint>Crystal:Crystal_HC49-U_Vertical</footprint>
      <libsource lib="Device" part="Crystal" description="Two pin crystal"/>
      <property name="Sheetname" value=""/>
      <property name="Sheetfile" value="SIMPLE-68008.kicad_sch"/>
      <sheetpath names="/" tstamps="/"/>
      <tstamps>c6e5ac4a-7028-4879-81d1-43f1b47f137e</tstamps>
    </comp>
  </components>
  <libparts>
    <libpart lib="CPU_NXP_68000" part="68008D">
      <description>16/32-bit Microprocessor, 8-bit databus</description>
      <docs>https://www.nxp.com/docs/en/reference-manual/MC68000UM.pdf</docs>
      <fields>
        <field name="Reference">U</field>
        <field name="Value">68008D</field>
        <field name="Datasheet">https://www.nxp.com/docs/en/reference-manual/MC68000UM.pdf</field>
      </fields>
      <pins>
        <pin num="1" name="A3" type="tri_state"/>
        <pin num="2" name="A4" type="tri_state"/>
        <pin num="3" name="A5" type="tri_state"/>
        <pin num="4" name="A6" type="tri_state"/>
        <pin num="5" name="A7" type="tri_state"/>
        <pin num="6" name="A8" type="tri_state"/>
        <pin num="7" name="A9" type="tri_state"/>
        <pin num="8" name="A10" type="tri_state"/>
        <pin num="9" name="A11" type="tri_state"/>
        <pin num="10" name="A12" type="tri_state"/>
        <pin num="11" name="A13" type="tri_state"/>
        <pin num="12" name="A14" type="tri_state"/>
        <pin num="13" name="VCC" type="power_in"/>
        <pin num="14" name="A15" type="tri_state"/>
        <pin num="15" name="GND" type="power_in"/>
        <pin num="16" name="A16" type="tri_state"/>
        <pin num="17" name="A17" type="tri_state"/>
        <pin num="18" name="A18" type="tri_state"/>
        <pin num="19" name="A19" type="tri_state"/>
        <pin num="20" name="D7" type="tri_state"/>
        <pin num="21" name="D6" type="tri_state"/>
        <pin num="22" name="D5" type="tri_state"/>
        <pin num="23" name="D4" type="tri_state"/>
        <pin num="24" name="D3" type="tri_state"/>
        <pin num="25" name="D2" type="tri_state"/>
        <pin num="26" name="D1" type="tri_state"/>
        <pin num="27" name="D0" type="tri_state"/>
        <pin num="28" name="AS" type="tri_state"/>
        <pin num="29" name="DS" type="tri_state"/>
        <pin num="30" name="R/W" type="tri_state"/>
        <pin num="31" name="DTACK" type="input"/>
        <pin num="32" name="BG" type="output"/>
        <pin num="33" name="BR" type="input"/>
        <pin num="34" name="CLK" type="input"/>
        <pin num="35" name="GND" type="power_in"/>
        <pin num="36" name="HALT" type="bidirectional"/>
        <pin num="37" name="RESET" type="bidirectional"/>
        <pin num="38" name="E" type="output"/>
        <pin num="39" name="VPA" type="input"/>
        <pin num="40" name="BERR" type="input"/>
        <pin num="41" name="IPL1" type="input"/>
        <pin num="42" name="IPL0/2" type="input"/>
        <pin num="43" name="FC2" type="output"/>
        <pin num="44" name="FC1" type="output"/>
        <pin num="45" name="FC0" type="output"/>
        <pin num="46" name="A0" type="tri_state"/>
        <pin num="47" name="A1" type="tri_state"/>
        <pin num="48" name="A2" type="tri_state"/>
      </pins>
    </libpart>
    <libpart lib="Connector_Generic" part="Conn_01x03">
      <description>Generic connector, single row, 01x03, script generated (kicad-library-utils/schlib/autogen/connector/)</description>
      <docs>~</docs>
      <footprints>
        <fp>Connector*:*_1x??_*</fp>
      </footprints>
      <fields>
        <field name="Reference">J</field>
        <field name="Value">Conn_01x03</field>
        <field name="Datasheet">~</field>
      </fields>
      <pins>
        <pin num="1" name="Pin_1" type="passive"/>
        <pin num="2" name="Pin_2" type="passive"/>
        <pin num="3" name="Pin_3" type="passive"/>
      </pins>
    </libpart>
    <libpart lib="Connector_Generic" part="Conn_01x06">
      <description>Generic connector, single row, 01x06, script generated (kicad-library-utils/schlib/autogen/connector/)</description>
      <docs>~</docs>
      <footprints>
        <fp>Connector*:*_1x??_*</fp>
      </footprints>
      <fields>
        <field name="Reference">J</field>
        <field name="Value">Conn_01x06</field>
        <field name="Datasheet">~</field>
      </fields>
      <pins>
        <pin num="1" name="Pin_1" type="passive"/>
        <pin num="2" name="Pin_2" type="passive"/>
        <pin num="3" name="Pin_3" type="passive"/>
        <pin num="4" name="Pin_4" type="passive"/>
        <pin num="5" name="Pin_5" type="passive"/>
        <pin num="6" name="Pin_6" type="passive"/>
      </pins>
    </libpart>
    <libpart lib="Connector_Generic" part="Conn_01x08">
      <description>Generic connector, single row, 01x08, script generated (kicad-library-utils/schlib/autogen/connector/)</description>
      <docs>~</docs>
      <footprints>
        <fp>Connector*:*_1x??_*</fp>
      </footprints>
      <fields>
        <field name="Reference">J</field>
        <field name="Value">Conn_01x08</field>
        <field name="Datasheet">~</field>
      </fields>
      <pins>
        <pin num="1" name="Pin_1" type="passive"/>
        <pin num="2" name="Pin_2" type="passive"/>
        <pin num="3" name="Pin_3" type="passive"/>
        <pin num="4" name="Pin_4" type="passive"/>
        <pin num="5" name="Pin_5" type="passive"/>
        <pin num="6" name="Pin_6" type="passive"/>
        <pin num="7" name="Pin_7" type="passive"/>
        <pin num="8" name="Pin_8" type="passive"/>
      </pins>
    </libpart>
    <libpart lib="Connector_Generic" part="Conn_02x04_Odd_Even">
      <description>Generic connector, double row, 02x04, odd/even pin numbering scheme (row 1 odd numbers, row 2 even numbers), script generated (kicad-library-utils/schlib/autogen/connector/)</description>
      <docs>~</docs>
      <footprints>
        <fp>Connector*:*_2x??_*</fp>
      </footprints>
      <fields>
        <field name="Reference">J</field>
        <field name="Value">Conn_02x04_Odd_Even</field>
        <field name="Datasheet">~</field>
      </fields>
      <pins>
        <pin num="1" name="Pin_1" type="passive"/>
        <pin num="2" name="Pin_2" type="passive"/>
        <pin num="3" name="Pin_3" type="passive"/>
        <pin num="4" name="Pin_4" type="passive"/>
        <pin num="5" name="Pin_5" type="passive"/>
        <pin num="6" name="Pin_6" type="passive"/>
        <pin num="7" name="Pin_7" type="passive"/>
        <pin num="8" name="Pin_8" type="passive"/>
      </pins>
    </libpart>
    <libpart lib="Connector_Generic" part="Conn_02x06_Odd_Even">
      <description>Generic connector, double row, 02x06, odd/even pin numbering scheme (row 1 odd numbers, row 2 even numbers), script generated (kicad-library-utils/schlib/autogen/connector/)</description>
      <docs>~</docs>
      <footprints>
        <fp>Connector*:*_2x??_*</fp>
      </footprints>
      <fields>
        <field name="Reference">J</field>
        <field name="Value">Conn_02x06_Odd_Even</field>
        <field name="Datasheet">~</field>
      </fields>
      <pins>
        <pin num="1" name="Pin_1" type="passive"/>
        <pin num="2" name="Pin_2" type="passive"/>
        <pin num="3" name="Pin_3" type="passive"/>
        <pin num="4" name="Pin_4" type="passive"/>
        <pin num="5" name="Pin_5" type="passive"/>
        <pin num="6" name="Pin_6" type="passive"/>
        <pin num="7" name="Pin_7" type="passive"/>
        <pin num="8" name="Pin_8" type="passive"/>
        <pin num="9" name="Pin_9" type="passive"/>
        <pin num="10" name="Pin_10" type="passive"/>
        <pin num="11" name="Pin_11" type="passive"/>
        <pin num="12" name="Pin_12" type="passive"/>
      </pins>
    </libpart>
    <libpart lib="Device" part="C_Small">
      <description>Unpolarized capacitor, small symbol</description>
      <docs>~</docs>
      <footprints>
        <fp>C_*</fp>
      </footprints>
      <fields>
        <field name="Reference">C</field>
        <field name="Value">C_Small</field>
        <field name="Datasheet">~</field>
      </fields>
      <pins>
        <pin num="1" name="" type="passive"/>
        <pin num="2" name="" type="passive"/>
      </pins>
    </libpart>
    <libpart lib="Device" part="Crystal">
      <description>Two pin crystal</description>
      <docs>~</docs>
      <footprints>
        <fp>Crystal*</fp>
      </footprints>
      <fields>
        <field name="Reference">Y</field>
        <field name="Value">Crystal</field>
        <field name="Datasheet">~</field>
      </fields>
      <pins>
        <pin num="1" name="1" type="passive"/>
        <pin num="2" name="2" type="passive"/>
      </pins>
    </libpart>
    <libpart lib="Device" part="R">
      <description>Resistor</description>
      <docs>~</docs>
      <footprints>
        <fp>R_*</fp>
      </footprints>
      <fields>
        <field name="Reference">R</field>
        <field name="Value">R</field>
        <field name="Datasheet">~</field>
      </fields>
      <pins>
        <pin num="1" name="" type="passive"/>
        <pin num="2" name="" type="passive"/>
      </pins>
    </libpart>
    <libpart lib="LandBoards" part="COUPON">
      <fields>
        <field name="Reference">COUP?</field>
        <field name="Value">COUPON</field>
      </fields>
    </libpart>
    <libpart lib="LandBoards" part="MTG_HOLE">
      <fields>
        <field name="Reference">MTG?</field>
        <field name="Value">MTG_HOLE</field>
      </fields>
    </libpart>
    <libpart lib="LandBoards_Semis" part="68681">
      <description>Interface serie 2 voies + 1 port parallele</description>
      <fields>
        <field name="Reference">U</field>
        <field name="Value">68681</field>
      </fields>
      <pins>
        <pin num="1" name="RS1" type="input"/>
        <pin num="2" name="IP3" type="input"/>
        <pin num="3" name="RS2" type="input"/>
        <pin num="4" name="IP1" type="input"/>
        <pin num="5" name="RS3" type="input"/>
        <pin num="6" name="RS4" type="input"/>
        <pin num="7" name="IP0" type="input"/>
        <pin num="8" name="R/~{W}" type="input"/>
        <pin num="9" name="~{DTACK}" type="open_collector"/>
        <pin num="10" name="RXDB" type="input"/>
        <pin num="11" name="TXDB" type="output"/>
        <pin num="12" name="OP1" type="output"/>
        <pin num="13" name="OP3" type="output"/>
        <pin num="14" name="OP5" type="output"/>
        <pin num="15" name="OP7" type="output"/>
        <pin num="16" name="D1" type="tri_state"/>
        <pin num="17" name="D3" type="tri_state"/>
        <pin num="18" name="D5" type="tri_state"/>
        <pin num="19" name="D7" type="tri_state"/>
        <pin num="20" name="GND" type="power_in"/>
        <pin num="21" name="~{IRQ}" type="output"/>
        <pin num="22" name="D6" type="tri_state"/>
        <pin num="23" name="D4" type="tri_state"/>
        <pin num="24" name="D2" type="tri_state"/>
        <pin num="25" name="D0" type="tri_state"/>
        <pin num="26" name="OP6" type="output"/>
        <pin num="27" name="OP4" type="output"/>
        <pin num="28" name="OP2" type="output"/>
        <pin num="29" name="OP0" type="output"/>
        <pin num="30" name="TXDA" type="output"/>
        <pin num="31" name="RXDA" type="input"/>
        <pin num="32" name="X1/CLK" type="input"/>
        <pin num="33" name="X2" type="input"/>
        <pin num="34" name="~{RESET}" type="input"/>
        <pin num="35" name="~{CS}" type="input"/>
        <pin num="36" name="IP2" type="input"/>
        <pin num="37" name="~{IACK}" type="input"/>
        <pin num="38" name="IP5" type="input"/>
        <pin num="39" name="IP4" type="input"/>
        <pin num="40" name="VCC" type="power_in"/>
      </pins>
    </libpart>
    <libpart lib="LandBoards_Semis" part="OSC">
      <fields>
        <field name="Reference">U</field>
        <field name="Value">OSC</field>
      </fields>
      <pins>
        <pin num="7" name="GND" type="power_in"/>
        <pin num="8" name="OUT" type="output"/>
        <pin num="14" name="VCC" type="power_in"/>
      </pins>
    </libpart>
    <libpart lib="Logic_Programmable" part="GAL16V8">
      <description>Programmable Logic Array, DIP-20/SOIC-20/PLCC-20</description>
      <footprints>
        <fp>DIP*</fp>
        <fp>PDIP*</fp>
        <fp>SOIC*</fp>
        <fp>SO*</fp>
        <fp>PLCC*</fp>
      </footprints>
      <fields>
        <field name="Reference">U</field>
        <field name="Value">GAL16V8</field>
      </fields>
      <pins>
        <pin num="1" name="I1/CLK" type="input"/>
        <pin num="2" name="I2" type="input"/>
        <pin num="3" name="I3" type="input"/>
        <pin num="4" name="I4" type="input"/>
        <pin num="5" name="I5" type="input"/>
        <pin num="6" name="I6" type="input"/>
        <pin num="7" name="I7" type="input"/>
        <pin num="8" name="I8" type="input"/>
        <pin num="9" name="I9" type="input"/>
        <pin num="10" name="GND" type="power_in"/>
        <pin num="11" name="I10/~{OE}" type="input"/>
        <pin num="12" name="IO8" type="tri_state"/>
        <pin num="13" name="IO7" type="tri_state"/>
        <pin num="14" name="IO6" type="tri_state"/>
        <pin num="15" name="IO5" type="tri_state"/>
        <pin num="16" name="IO4" type="tri_state"/>
        <pin num="17" name="I03" type="tri_state"/>
        <pin num="18" name="IO2" type="tri_state"/>
        <pin num="19" name="IO1" type="tri_state"/>
        <pin num="20" name="VCC" type="power_in"/>
      </pins>
    </libpart>
    <libpart lib="Memory_EPROM" part="27C010">
      <description>OTP EPROM 1 MiBit (128 Ki x 8 Bit)</description>
      <docs>http://ww1.microchip.com/downloads/en/DeviceDoc/doc0321.pdf</docs>
      <footprints>
        <fp>DIP*W15.24mm*</fp>
        <fp>PLCC*</fp>
      </footprints>
      <fields>
        <field name="Reference">U</field>
        <field name="Value">27C010</field>
        <field name="Datasheet">http://ww1.microchip.com/downloads/en/DeviceDoc/doc0321.pdf</field>
      </fields>
      <pins>
        <pin num="1" name="VPP" type="input"/>
        <pin num="2" name="A16" type="input"/>
        <pin num="3" name="A15" type="input"/>
        <pin num="4" name="A12" type="input"/>
        <pin num="5" name="A7" type="input"/>
        <pin num="6" name="A6" type="input"/>
        <pin num="7" name="A5" type="input"/>
        <pin num="8" name="A4" type="input"/>
        <pin num="9" name="A3" type="input"/>
        <pin num="10" name="A2" type="input"/>
        <pin num="11" name="A1" type="input"/>
        <pin num="12" name="A0" type="input"/>
        <pin num="13" name="D0" type="tri_state"/>
        <pin num="14" name="D1" type="tri_state"/>
        <pin num="15" name="D2" type="tri_state"/>
        <pin num="16" name="GND" type="power_in"/>
        <pin num="17" name="D3" type="tri_state"/>
        <pin num="18" name="D4" type="tri_state"/>
        <pin num="19" name="D5" type="tri_state"/>
        <pin num="20" name="D6" type="tri_state"/>
        <pin num="21" name="D7" type="tri_state"/>
        <pin num="22" name="~{CE}" type="input"/>
        <pin num="23" name="A10" type="input"/>
        <pin num="24" name="~{OE}" type="input"/>
        <pin num="25" name="A11" type="input"/>
        <pin num="26" name="A9" type="input"/>
        <pin num="27" name="A8" type="input"/>
        <pin num="28" name="A13" type="input"/>
        <pin num="29" name="A14" type="input"/>
        <pin num="31" name="~{PGM}" type="input"/>
        <pin num="32" name="VCC" type="power_in"/>
      </pins>
    </libpart>
    <libpart lib="Memory_EPROM" part="27C020">
      <description>OTP EPROM 2 MiBit (256 Ki x 8 Bit)</description>
      <docs>http://ww1.microchip.com/downloads/en/devicedoc/doc0570.pdf</docs>
      <footprints>
        <fp>DIP*W15.24mm*</fp>
        <fp>PLCC*</fp>
      </footprints>
      <fields>
        <field name="Reference">U</field>
        <field name="Value">27C020</field>
        <field name="Datasheet">http://ww1.microchip.com/downloads/en/devicedoc/doc0570.pdf</field>
      </fields>
      <pins>
        <pin num="1" name="VPP" type="input"/>
        <pin num="2" name="A16" type="input"/>
        <pin num="3" name="A15" type="input"/>
        <pin num="4" name="A12" type="input"/>
        <pin num="5" name="A7" type="input"/>
        <pin num="6" name="A6" type="input"/>
        <pin num="7" name="A5" type="input"/>
        <pin num="8" name="A4" type="input"/>
        <pin num="9" name="A3" type="input"/>
        <pin num="10" name="A2" type="input"/>
        <pin num="11" name="A1" type="input"/>
        <pin num="12" name="A0" type="input"/>
        <pin num="13" name="D0" type="tri_state"/>
        <pin num="14" name="D1" type="tri_state"/>
        <pin num="15" name="D2" type="tri_state"/>
        <pin num="16" name="GND" type="power_in"/>
        <pin num="17" name="D3" type="tri_state"/>
        <pin num="18" name="D4" type="tri_state"/>
        <pin num="19" name="D5" type="tri_state"/>
        <pin num="20" name="D6" type="tri_state"/>
        <pin num="21" name="D7" type="tri_state"/>
        <pin num="22" name="~{CE}" type="input"/>
        <pin num="23" name="A10" type="input"/>
        <pin num="24" name="~{OE}" type="input"/>
        <pin num="25" name="A11" type="input"/>
        <pin num="26" name="A9" type="input"/>
        <pin num="27" name="A8" type="input"/>
        <pin num="28" name="A13" type="input"/>
        <pin num="29" name="A14" type="input"/>
        <pin num="30" name="A17" type="input"/>
        <pin num="31" name="~{PGM}" type="input"/>
        <pin num="32" name="VCC" type="power_in"/>
      </pins>
    </libpart>
    <libpart lib="Memory_EPROM" part="27C040">
      <description>OTP EPROM 4 MiBit (512 Ki x 8)</description>
      <docs>http://ww1.microchip.com/downloads/en/devicedoc/doc0189.pdf</docs>
      <footprints>
        <fp>DIP*W15.24mm*</fp>
        <fp>PLCC*</fp>
      </footprints>
      <fields>
        <field name="Reference">U</field>
        <field name="Value">27C040</field>
        <field name="Datasheet">http://ww1.microchip.com/downloads/en/devicedoc/doc0189.pdf</field>
      </fields>
      <pins>
        <pin num="1" name="VPP" type="input"/>
        <pin num="2" name="A16" type="input"/>
        <pin num="3" name="A15" type="input"/>
        <pin num="4" name="A12" type="input"/>
        <pin num="5" name="A7" type="input"/>
        <pin num="6" name="A6" type="input"/>
        <pin num="7" name="A5" type="input"/>
        <pin num="8" name="A4" type="input"/>
        <pin num="9" name="A3" type="input"/>
        <pin num="10" name="A2" type="input"/>
        <pin num="11" name="A1" type="input"/>
        <pin num="12" name="A0" type="input"/>
        <pin num="13" name="D0" type="tri_state"/>
        <pin num="14" name="D1" type="tri_state"/>
        <pin num="15" name="D2" type="tri_state"/>
        <pin num="16" name="GND" type="power_in"/>
        <pin num="17" name="D3" type="tri_state"/>
        <pin num="18" name="D4" type="tri_state"/>
        <pin num="19" name="D5" type="tri_state"/>
        <pin num="20" name="D6" type="tri_state"/>
        <pin num="21" name="D7" type="tri_state"/>
        <pin num="22" name="~{CE}" type="input"/>
        <pin num="23" name="A10" type="input"/>
        <pin num="24" name="~{OE}" type="input"/>
        <pin num="25" name="A11" type="input"/>
        <pin num="26" name="A9" type="input"/>
        <pin num="27" name="A8" type="input"/>
        <pin num="28" name="A13" type="input"/>
        <pin num="29" name="A14" type="input"/>
        <pin num="30" name="A17" type="input"/>
        <pin num="31" name="A18" type="input"/>
        <pin num="32" name="VCC" type="power_in"/>
      </pins>
    </libpart>
    <libpart lib="Memory_EPROM" part="27C128">
      <description>OTP EPROM 128 KiBit, [Obsolete 2004-01]</description>
      <docs>http://ww1.microchip.com/downloads/en/devicedoc/11003L.pdf</docs>
      <footprints>
        <fp>DIP*W15.24mm*</fp>
      </footprints>
      <fields>
        <field name="Reference">U</field>
        <field name="Value">27C128</field>
        <field name="Footprint">Package_DIP:DIP-28_W15.24mm</field>
        <field name="Datasheet">http://ww1.microchip.com/downloads/en/devicedoc/11003L.pdf</field>
      </fields>
      <pins>
        <pin num="1" name="VPP" type="input"/>
        <pin num="2" name="A12" type="input"/>
        <pin num="3" name="A7" type="input"/>
        <pin num="4" name="A6" type="input"/>
        <pin num="5" name="A5" type="input"/>
        <pin num="6" name="A4" type="input"/>
        <pin num="7" name="A3" type="input"/>
        <pin num="8" name="A2" type="input"/>
        <pin num="9" name="A1" type="input"/>
        <pin num="10" name="A0" type="input"/>
        <pin num="11" name="D0" type="tri_state"/>
        <pin num="12" name="D1" type="tri_state"/>
        <pin num="13" name="D2" type="tri_state"/>
        <pin num="14" name="GND" type="power_in"/>
        <pin num="15" name="D3" type="tri_state"/>
        <pin num="16" name="D4" type="tri_state"/>
        <pin num="17" name="D5" type="tri_state"/>
        <pin num="18" name="D6" type="tri_state"/>
        <pin num="19" name="D7" type="tri_state"/>
        <pin num="20" name="~{CE}" type="input"/>
        <pin num="21" name="A10" type="input"/>
        <pin num="22" name="~{OE}" type="input"/>
        <pin num="23" name="A11" type="input"/>
        <pin num="24" name="A9" type="input"/>
        <pin num="25" name="A8" type="input"/>
        <pin num="26" name="A13" type="input"/>
        <pin num="27" name="~{PGM}" type="input"/>
        <pin num="28" name="VCC" type="power_in"/>
      </pins>
    </libpart>
    <libpart lib="Memory_EPROM" part="27C256">
      <description>OTP EPROM 256 KiBit</description>
      <docs>http://ww1.microchip.com/downloads/en/DeviceDoc/doc0014.pdf</docs>
      <footprints>
        <fp>DIP*W15.24mm*</fp>
      </footprints>
      <fields>
        <field name="Reference">U</field>
        <field name="Value">27C256</field>
        <field name="Footprint">Package_DIP:DIP-28_W15.24mm</field>
        <field name="Datasheet">http://ww1.microchip.com/downloads/en/DeviceDoc/doc0014.pdf</field>
      </fields>
      <pins>
        <pin num="1" name="VPP" type="input"/>
        <pin num="2" name="A12" type="input"/>
        <pin num="3" name="A7" type="input"/>
        <pin num="4" name="A6" type="input"/>
        <pin num="5" name="A5" type="input"/>
        <pin num="6" name="A4" type="input"/>
        <pin num="7" name="A3" type="input"/>
        <pin num="8" name="A2" type="input"/>
        <pin num="9" name="A1" type="input"/>
        <pin num="10" name="A0" type="input"/>
        <pin num="11" name="D0" type="tri_state"/>
        <pin num="12" name="D1" type="tri_state"/>
        <pin num="13" name="D2" type="tri_state"/>
        <pin num="14" name="GND" type="power_in"/>
        <pin num="15" name="D3" type="tri_state"/>
        <pin num="16" name="D4" type="tri_state"/>
        <pin num="17" name="D5" type="tri_state"/>
        <pin num="18" name="D6" type="tri_state"/>
        <pin num="19" name="D7" type="tri_state"/>
        <pin num="20" name="~{CE}" type="input"/>
        <pin num="21" name="A10" type="input"/>
        <pin num="22" name="~{OE}" type="input"/>
        <pin num="23" name="A11" type="input"/>
        <pin num="24" name="A9" type="input"/>
        <pin num="25" name="A8" type="input"/>
        <pin num="26" name="A13" type="input"/>
        <pin num="27" name="A14" type="input"/>
        <pin num="28" name="VCC" type="power_in"/>
      </pins>
    </libpart>
    <libpart lib="Memory_EPROM" part="27C512">
      <description>OTP EPROM 512 KiBit</description>
      <docs>http://ww1.microchip.com/downloads/en/DeviceDoc/doc0015.pdf</docs>
      <footprints>
        <fp>DIP*W15.24mm*</fp>
      </footprints>
      <fields>
        <field name="Reference">U</field>
        <field name="Value">27C512</field>
        <field name="Footprint">Package_DIP:DIP-28_W15.24mm</field>
        <field name="Datasheet">http://ww1.microchip.com/downloads/en/DeviceDoc/doc0015.pdf</field>
      </fields>
      <pins>
        <pin num="1" name="A15" type="input"/>
        <pin num="2" name="A12" type="input"/>
        <pin num="3" name="A7" type="input"/>
        <pin num="4" name="A6" type="input"/>
        <pin num="5" name="A5" type="input"/>
        <pin num="6" name="A4" type="input"/>
        <pin num="7" name="A3" type="input"/>
        <pin num="8" name="A2" type="input"/>
        <pin num="9" name="A1" type="input"/>
        <pin num="10" name="A0" type="input"/>
        <pin num="11" name="D0" type="tri_state"/>
        <pin num="12" name="D1" type="tri_state"/>
        <pin num="13" name="D2" type="tri_state"/>
        <pin num="14" name="GND" type="power_in"/>
        <pin num="15" name="D3" type="tri_state"/>
        <pin num="16" name="D4" type="tri_state"/>
        <pin num="17" name="D5" type="tri_state"/>
        <pin num="18" name="D6" type="tri_state"/>
        <pin num="19" name="D7" type="tri_state"/>
        <pin num="20" name="~{CE}" type="input"/>
        <pin num="21" name="A10" type="input"/>
        <pin num="22" name="~{OE}" type="input"/>
        <pin num="23" name="A11" type="input"/>
        <pin num="24" name="A9" type="input"/>
        <pin num="25" name="A8" type="input"/>
        <pin num="26" name="A13" type="input"/>
        <pin num="27" name="A14" type="input"/>
        <pin num="28" name="VCC" type="power_in"/>
      </pins>
    </libpart>
    <libpart lib="Memory_EPROM" part="27C64">
      <description>OTP EPROM 64 KiBit, [Obsolete 2004-01]</description>
      <docs>http://ww1.microchip.com/downloads/en/DeviceDoc/11107M.pdf</docs>
      <footprints>
        <fp>DIP*W15.24mm*</fp>
      </footprints>
      <fields>
        <field name="Reference">U</field>
        <field name="Value">27C64</field>
        <field name="Footprint">Package_DIP:DIP-28_W15.24mm</field>
        <field name="Datasheet">http://ww1.microchip.com/downloads/en/DeviceDoc/11107M.pdf</field>
      </fields>
      <pins>
        <pin num="1" name="VPP" type="input"/>
        <pin num="2" name="A12" type="input"/>
        <pin num="3" name="A7" type="input"/>
        <pin num="4" name="A6" type="input"/>
        <pin num="5" name="A5" type="input"/>
        <pin num="6" name="A4" type="input"/>
        <pin num="7" name="A3" type="input"/>
        <pin num="8" name="A2" type="input"/>
        <pin num="9" name="A1" type="input"/>
        <pin num="10" name="A0" type="input"/>
        <pin num="11" name="D0" type="tri_state"/>
        <pin num="12" name="D1" type="tri_state"/>
        <pin num="13" name="D2" type="tri_state"/>
        <pin num="14" name="GND" type="power_in"/>
        <pin num="15" name="D3" type="tri_state"/>
        <pin num="16" name="D4" type="tri_state"/>
        <pin num="17" name="D5" type="tri_state"/>
        <pin num="18" name="D6" type="tri_state"/>
        <pin num="19" name="D7" type="tri_state"/>
        <pin num="20" name="~{CE}" type="input"/>
        <pin num="21" name="A10" type="input"/>
        <pin num="22" name="~{OE}" type="input"/>
        <pin num="23" name="A11" type="input"/>
        <pin num="24" name="A9" type="input"/>
        <pin num="25" name="A8" type="input"/>
        <pin num="26" name="NC" type="no_connect"/>
        <pin num="27" name="~{PGM}" type="input"/>
        <pin num="28" name="VCC" type="power_in"/>
      </pins>
    </libpart>
    <libpart lib="Memory_RAM" part="AS6C4008-55PCN">
      <description>512K x 8 Low Power CMOS RAM, DIP-32</description>
      <docs>https://www.alliancememory.com/wp-content/uploads/pdf/AS6C4008.pdf</docs>
      <footprints>
        <fp>DIP*W15.24mm*</fp>
      </footprints>
      <fields>
        <field name="Reference">U</field>
        <field name="Value">AS6C4008-55PCN</field>
        <field name="Footprint">Package_DIP:DIP-32_W15.24mm</field>
        <field name="Datasheet">https://www.alliancememory.com/wp-content/uploads/pdf/AS6C4008.pdf</field>
      </fields>
      <pins>
        <pin num="1" name="A18" type="input"/>
        <pin num="2" name="A16" type="input"/>
        <pin num="3" name="A14" type="input"/>
        <pin num="4" name="A12" type="input"/>
        <pin num="5" name="A7" type="input"/>
        <pin num="6" name="A6" type="input"/>
        <pin num="7" name="A5" type="input"/>
        <pin num="8" name="A4" type="input"/>
        <pin num="9" name="A3" type="input"/>
        <pin num="10" name="A2" type="input"/>
        <pin num="11" name="A1" type="input"/>
        <pin num="12" name="A0" type="input"/>
        <pin num="13" name="DQ0" type="tri_state"/>
        <pin num="14" name="DQ1" type="tri_state"/>
        <pin num="15" name="DQ2" type="tri_state"/>
        <pin num="16" name="VSS" type="power_in"/>
        <pin num="17" name="DQ3" type="tri_state"/>
        <pin num="18" name="DQ4" type="tri_state"/>
        <pin num="19" name="DQ5" type="tri_state"/>
        <pin num="20" name="DQ6" type="tri_state"/>
        <pin num="21" name="DQ7" type="tri_state"/>
        <pin num="22" name="CE#" type="input"/>
        <pin num="23" name="A10" type="input"/>
        <pin num="24" name="OE#" type="input"/>
        <pin num="25" name="A11" type="input"/>
        <pin num="26" name="A9" type="input"/>
        <pin num="27" name="A8" type="input"/>
        <pin num="28" name="A13" type="input"/>
        <pin num="29" name="WE#" type="input"/>
        <pin num="30" name="A17" type="input"/>
        <pin num="31" name="A15" type="input"/>
        <pin num="32" name="VCC" type="power_in"/>
      </pins>
    </libpart>
    <libpart lib="Switch" part="SW_Push">
      <description>Push button switch, generic, two pins</description>
      <docs>~</docs>
      <fields>
        <field name="Reference">SW</field>
        <field name="Value">SW_Push</field>
        <field name="Datasheet">~</field>
      </fields>
      <pins>
        <pin num="1" name="1" type="passive"/>
        <pin num="2" name="2" type="passive"/>
      </pins>
    </libpart>
  </libparts>
  <libraries>
    <library logical="CPU_NXP_68000">
      <uri>C:\Program Files\KiCad\6.0\share\kicad\symbols\/CPU_NXP_68000.kicad_sym</uri>
    </library>
    <library logical="Connector_Generic">
      <uri>C:\Program Files\KiCad\6.0\share\kicad\symbols\/Connector_Generic.kicad_sym</uri>
    </library>
    <library logical="Device">
      <uri>C:\Program Files\KiCad\6.0\share\kicad\symbols\/Device.kicad_sym</uri>
    </library>
    <library logical="LandBoards">
      <uri>C:/Users/HPz420/Documents/GitHub/land-boards/lb-boards/KiCAD/library/LandBoards.kicad_sym</uri>
    </library>
    <library logical="LandBoards_Semis">
      <uri>C:/Users/HPz420/Documents/GitHub/land-boards/lb-boards/KiCAD/library/LandBoards_Semis.kicad_sym</uri>
    </library>
    <library logical="Logic_Programmable">
      <uri>C:\Program Files\KiCad\6.0\share\kicad\symbols\/Logic_Programmable.kicad_sym</uri>
    </library>
    <library logical="Memory_EPROM">
      <uri>C:\Program Files\KiCad\6.0\share\kicad\symbols\/Memory_EPROM.kicad_sym</uri>
    </library>
    <library logical="Memory_RAM">
      <uri>C:\Program Files\KiCad\6.0\share\kicad\symbols\/Memory_RAM.kicad_sym</uri>
    </library>
    <library logical="Switch">
      <uri>C:\Program Files\KiCad\6.0\share\kicad\symbols\/Switch.kicad_sym</uri>
    </library>
  </libraries>
  <nets>
    <net code="1" name="/CPUA0">
      <node ref="U5" pin="46" pinfunction="A0" pintype="tri_state"/>
      <node ref="U7" pin="12" pinfunction="A0" pintype="input"/>
      <node ref="U8" pin="12" pinfunction="A0" pintype="input"/>
    </net>
    <net code="2" name="/CPUA1">
      <node ref="U5" pin="47" pinfunction="A1" pintype="tri_state"/>
      <node ref="U6" pin="1" pinfunction="RS1" pintype="input"/>
      <node ref="U7" pin="11" pinfunction="A1" pintype="input"/>
      <node ref="U8" pin="11" pinfunction="A1" pintype="input"/>
    </net>
    <net code="3" name="/CPUA2">
      <node ref="U5" pin="48" pinfunction="A2" pintype="tri_state"/>
      <node ref="U6" pin="3" pinfunction="RS2" pintype="input"/>
      <node ref="U7" pin="10" pinfunction="A2" pintype="input"/>
      <node ref="U8" pin="10" pinfunction="A2" pintype="input"/>
    </net>
    <net code="4" name="/CPUA3">
      <node ref="U5" pin="1" pinfunction="A3" pintype="tri_state"/>
      <node ref="U6" pin="5" pinfunction="RS3" pintype="input"/>
      <node ref="U7" pin="9" pinfunction="A3" pintype="input"/>
      <node ref="U8" pin="9" pinfunction="A3" pintype="input"/>
    </net>
    <net code="5" name="/CPUA4">
      <node ref="U5" pin="2" pinfunction="A4" pintype="tri_state"/>
      <node ref="U6" pin="6" pinfunction="RS4" pintype="input"/>
      <node ref="U7" pin="8" pinfunction="A4" pintype="input"/>
      <node ref="U8" pin="8" pinfunction="A4" pintype="input"/>
    </net>
    <net code="6" name="/CPUA5">
      <node ref="U5" pin="3" pinfunction="A5" pintype="tri_state"/>
      <node ref="U7" pin="7" pinfunction="A5" pintype="input"/>
      <node ref="U8" pin="7" pinfunction="A5" pintype="input"/>
    </net>
    <net code="7" name="/CPUA6">
      <node ref="U5" pin="4" pinfunction="A6" pintype="tri_state"/>
      <node ref="U7" pin="6" pinfunction="A6" pintype="input"/>
      <node ref="U8" pin="6" pinfunction="A6" pintype="input"/>
    </net>
    <net code="8" name="/CPUA7">
      <node ref="U5" pin="5" pinfunction="A7" pintype="tri_state"/>
      <node ref="U7" pin="5" pinfunction="A7" pintype="input"/>
      <node ref="U8" pin="5" pinfunction="A7" pintype="input"/>
    </net>
    <net code="9" name="/CPUA8">
      <node ref="U5" pin="6" pinfunction="A8" pintype="tri_state"/>
      <node ref="U7" pin="27" pinfunction="A8" pintype="input"/>
      <node ref="U8" pin="27" pinfunction="A8" pintype="input"/>
    </net>
    <net code="10" name="/CPUA9">
      <node ref="U5" pin="7" pinfunction="A9" pintype="tri_state"/>
      <node ref="U7" pin="26" pinfunction="A9" pintype="input"/>
      <node ref="U8" pin="26" pinfunction="A9" pintype="input"/>
    </net>
    <net code="11" name="/CPUA10">
      <node ref="U5" pin="8" pinfunction="A10" pintype="tri_state"/>
      <node ref="U7" pin="23" pinfunction="A10" pintype="input"/>
      <node ref="U8" pin="23" pinfunction="A10" pintype="input"/>
    </net>
    <net code="12" name="/CPUA11">
      <node ref="U5" pin="9" pinfunction="A11" pintype="tri_state"/>
      <node ref="U7" pin="25" pinfunction="A11" pintype="input"/>
      <node ref="U8" pin="25" pinfunction="A11" pintype="input"/>
    </net>
    <net code="13" name="/CPUA12">
      <node ref="U5" pin="10" pinfunction="A12" pintype="tri_state"/>
      <node ref="U7" pin="4" pinfunction="A12" pintype="input"/>
      <node ref="U8" pin="4" pinfunction="A12" pintype="input"/>
    </net>
    <net code="14" name="/CPUA13">
      <node ref="U5" pin="11" pinfunction="A13" pintype="tri_state"/>
      <node ref="U7" pin="28" pinfunction="A13" pintype="input"/>
      <node ref="U8" pin="28" pinfunction="A13" pintype="input"/>
    </net>
    <net code="15" name="/CPUA14">
      <node ref="H5" pin="3" pinfunction="Pin_3" pintype="passive"/>
      <node ref="U5" pin="12" pinfunction="A14" pintype="tri_state"/>
      <node ref="U7" pin="3" pinfunction="A14" pintype="input"/>
    </net>
    <net code="16" name="/CPUA15">
      <node ref="H3" pin="3" pinfunction="Pin_3" pintype="passive"/>
      <node ref="U5" pin="14" pinfunction="A15" pintype="tri_state"/>
      <node ref="U7" pin="31" pinfunction="A15" pintype="input"/>
    </net>
    <net code="17" name="/CPUA16">
      <node ref="U2" pin="4" pinfunction="I4" pintype="input"/>
      <node ref="U3" pin="4" pinfunction="I4" pintype="input"/>
      <node ref="U5" pin="16" pinfunction="A16" pintype="tri_state"/>
      <node ref="U7" pin="2" pinfunction="A16" pintype="input"/>
      <node ref="U8" pin="2" pinfunction="A16" pintype="input"/>
    </net>
    <net code="18" name="/CPUA17">
      <node ref="H4" pin="3" pinfunction="Pin_3" pintype="passive"/>
      <node ref="H6" pin="3" pinfunction="Pin_3" pintype="passive"/>
      <node ref="U2" pin="5" pinfunction="I5" pintype="input"/>
      <node ref="U3" pin="5" pinfunction="I5" pintype="input"/>
      <node ref="U5" pin="17" pinfunction="A17" pintype="tri_state"/>
    </net>
    <net code="19" name="/CPUA18">
      <node ref="H2" pin="3" pinfunction="Pin_3" pintype="passive"/>
      <node ref="U2" pin="6" pinfunction="I6" pintype="input"/>
      <node ref="U3" pin="6" pinfunction="I6" pintype="input"/>
      <node ref="U5" pin="18" pinfunction="A18" pintype="tri_state"/>
      <node ref="U7" pin="1" pinfunction="A18" pintype="input"/>
    </net>
    <net code="20" name="/CPUA19">
      <node ref="U2" pin="7" pinfunction="I7" pintype="input"/>
      <node ref="U3" pin="7" pinfunction="I7" pintype="input"/>
      <node ref="U5" pin="19" pinfunction="A19" pintype="tri_state"/>
    </net>
    <net code="21" name="/CPUAS*">
      <node ref="U2" pin="2" pinfunction="I2" pintype="input"/>
      <node ref="U5" pin="28" pinfunction="AS" pintype="tri_state"/>
    </net>
    <net code="22" name="/CPUCLK">
      <node ref="U1" pin="8" pinfunction="OUT" pintype="output"/>
      <node ref="U2" pin="1" pinfunction="I1/CLK" pintype="input"/>
      <node ref="U3" pin="1" pinfunction="I1/CLK" pintype="input"/>
      <node ref="U5" pin="34" pinfunction="CLK" pintype="input"/>
    </net>
    <net code="23" name="/CPUD0">
      <node ref="U3" pin="9" pinfunction="I9" pintype="input"/>
      <node ref="U5" pin="27" pinfunction="D0" pintype="tri_state"/>
      <node ref="U6" pin="25" pinfunction="D0" pintype="tri_state"/>
      <node ref="U7" pin="13" pinfunction="DQ0" pintype="tri_state"/>
      <node ref="U8" pin="13" pinfunction="D0" pintype="tri_state"/>
    </net>
    <net code="24" name="/CPUD1">
      <node ref="U5" pin="26" pinfunction="D1" pintype="tri_state"/>
      <node ref="U6" pin="16" pinfunction="D1" pintype="tri_state"/>
      <node ref="U7" pin="14" pinfunction="DQ1" pintype="tri_state"/>
      <node ref="U8" pin="14" pinfunction="D1" pintype="tri_state"/>
    </net>
    <net code="25" name="/CPUD2">
      <node ref="U5" pin="25" pinfunction="D2" pintype="tri_state"/>
      <node ref="U6" pin="24" pinfunction="D2" pintype="tri_state"/>
      <node ref="U7" pin="15" pinfunction="DQ2" pintype="tri_state"/>
      <node ref="U8" pin="15" pinfunction="D2" pintype="tri_state"/>
    </net>
    <net code="26" name="/CPUD3">
      <node ref="U5" pin="24" pinfunction="D3" pintype="tri_state"/>
      <node ref="U6" pin="17" pinfunction="D3" pintype="tri_state"/>
      <node ref="U7" pin="17" pinfunction="DQ3" pintype="tri_state"/>
      <node ref="U8" pin="17" pinfunction="D3" pintype="tri_state"/>
    </net>
    <net code="27" name="/CPUD4">
      <node ref="U5" pin="23" pinfunction="D4" pintype="tri_state"/>
      <node ref="U6" pin="23" pinfunction="D4" pintype="tri_state"/>
      <node ref="U7" pin="18" pinfunction="DQ4" pintype="tri_state"/>
      <node ref="U8" pin="18" pinfunction="D4" pintype="tri_state"/>
    </net>
    <net code="28" name="/CPUD5">
      <node ref="U5" pin="22" pinfunction="D5" pintype="tri_state"/>
      <node ref="U6" pin="18" pinfunction="D5" pintype="tri_state"/>
      <node ref="U7" pin="19" pinfunction="DQ5" pintype="tri_state"/>
      <node ref="U8" pin="19" pinfunction="D5" pintype="tri_state"/>
    </net>
    <net code="29" name="/CPUD6">
      <node ref="U5" pin="21" pinfunction="D6" pintype="tri_state"/>
      <node ref="U6" pin="22" pinfunction="D6" pintype="tri_state"/>
      <node ref="U7" pin="20" pinfunction="DQ6" pintype="tri_state"/>
      <node ref="U8" pin="20" pinfunction="D6" pintype="tri_state"/>
    </net>
    <net code="30" name="/CPUD7">
      <node ref="U5" pin="20" pinfunction="D7" pintype="tri_state"/>
      <node ref="U6" pin="19" pinfunction="D7" pintype="tri_state"/>
      <node ref="U7" pin="21" pinfunction="DQ7" pintype="tri_state"/>
      <node ref="U8" pin="21" pinfunction="D7" pintype="tri_state"/>
    </net>
    <net code="31" name="/CPUDS*">
      <node ref="U2" pin="3" pinfunction="I3" pintype="input"/>
      <node ref="U3" pin="3" pinfunction="I3" pintype="input"/>
      <node ref="U5" pin="29" pinfunction="DS" pintype="tri_state"/>
    </net>
    <net code="32" name="/CPUHLT*">
      <node ref="R2" pin="2" pintype="passive"/>
      <node ref="U3" pin="18" pinfunction="IO2" pintype="tri_state"/>
      <node ref="U5" pin="36" pinfunction="HALT" pintype="bidirectional"/>
    </net>
    <net code="33" name="/CPUIACK*">
      <node ref="U2" pin="14" pinfunction="IO6" pintype="tri_state"/>
      <node ref="U6" pin="37" pinfunction="~{IACK}" pintype="input"/>
    </net>
    <net code="34" name="/CPURES*">
      <node ref="R1" pin="2" pintype="passive"/>
      <node ref="U3" pin="19" pinfunction="IO1" pintype="tri_state"/>
      <node ref="U5" pin="37" pinfunction="RESET" pintype="bidirectional"/>
      <node ref="U6" pin="34" pinfunction="~{RESET}" pintype="input"/>
    </net>
    <net code="35" name="/CPUWR*">
      <node ref="U3" pin="2" pinfunction="I2" pintype="input"/>
      <node ref="U5" pin="30" pinfunction="R/W" pintype="tri_state"/>
      <node ref="U6" pin="8" pinfunction="R/~{W}" pintype="input"/>
      <node ref="U7" pin="29" pinfunction="WE#" pintype="input"/>
    </net>
    <net code="36" name="/CTSA*">
      <node ref="J1" pin="4" pinfunction="Pin_4" pintype="passive"/>
      <node ref="U6" pin="7" pinfunction="IP0" pintype="input"/>
    </net>
    <net code="37" name="/CTSB*">
      <node ref="J1" pin="3" pinfunction="Pin_3" pintype="passive"/>
      <node ref="U6" pin="4" pinfunction="IP1" pintype="input"/>
    </net>
    <net code="38" name="/DDTACK*">
      <node ref="R5" pin="2" pintype="passive"/>
      <node ref="U2" pin="12" pinfunction="IO8" pintype="tri_state"/>
      <node ref="U6" pin="9" pinfunction="~{DTACK}" pintype="open_collector"/>
    </net>
    <net code="39" name="/DTACK*">
      <node ref="U2" pin="16" pinfunction="IO4" pintype="tri_state"/>
      <node ref="U5" pin="31" pinfunction="DTACK" pintype="input"/>
    </net>
    <net code="40" name="/DUARTCS*">
      <node ref="U2" pin="15" pinfunction="IO5" pintype="tri_state"/>
      <node ref="U6" pin="35" pinfunction="~{CS}" pintype="input"/>
    </net>
    <net code="41" name="/EE_PIN3">
      <node ref="H3" pin="2" pinfunction="Pin_2" pintype="passive"/>
      <node ref="U8" pin="3" pinfunction="A15" pintype="input"/>
    </net>
    <net code="42" name="/EE_PIN29">
      <node ref="H5" pin="2" pinfunction="Pin_2" pintype="passive"/>
      <node ref="U8" pin="29" pinfunction="A14" pintype="input"/>
    </net>
    <net code="43" name="/EE_PIN30">
      <node ref="H4" pin="2" pinfunction="Pin_2" pintype="passive"/>
      <node ref="U8" pin="30" pinfunction="A17" pintype="input"/>
    </net>
    <net code="44" name="/EE_PIN31">
      <node ref="H2" pin="2" pinfunction="Pin_2" pintype="passive"/>
      <node ref="U8" pin="31" pinfunction="A18" pintype="input"/>
    </net>
    <net code="45" name="/FC0">
      <node ref="U2" pin="8" pinfunction="I8" pintype="input"/>
      <node ref="U5" pin="45" pinfunction="FC0" pintype="output"/>
    </net>
    <net code="46" name="/FC1">
      <node ref="U2" pin="9" pinfunction="I9" pintype="input"/>
      <node ref="U5" pin="44" pinfunction="FC1" pintype="output"/>
    </net>
    <net code="47" name="/FC2">
      <node ref="U2" pin="11" pinfunction="I10/~{OE}" pintype="input"/>
      <node ref="U5" pin="43" pinfunction="FC2" pintype="output"/>
    </net>
    <net code="48" name="/IP2">
      <node ref="J2" pin="1" pinfunction="Pin_1" pintype="passive"/>
      <node ref="U6" pin="36" pinfunction="IP2" pintype="input"/>
    </net>
    <net code="49" name="/IP3">
      <node ref="J2" pin="4" pinfunction="Pin_4" pintype="passive"/>
      <node ref="U6" pin="2" pinfunction="IP3" pintype="input"/>
    </net>
    <net code="50" name="/IP4">
      <node ref="J2" pin="3" pinfunction="Pin_3" pintype="passive"/>
      <node ref="U6" pin="39" pinfunction="IP4" pintype="input"/>
    </net>
    <net code="51" name="/IP5">
      <node ref="J2" pin="2" pinfunction="Pin_2" pintype="passive"/>
      <node ref="U6" pin="38" pinfunction="IP5" pintype="input"/>
    </net>
    <net code="52" name="/IRQ*">
      <node ref="R6" pin="2" pintype="passive"/>
      <node ref="U5" pin="41" pinfunction="IPL1" pintype="input"/>
      <node ref="U6" pin="21" pinfunction="~{IRQ}" pintype="output"/>
    </net>
    <net code="53" name="/MEMRD*">
      <node ref="U3" pin="16" pinfunction="IO4" pintype="tri_state"/>
      <node ref="U7" pin="24" pinfunction="OE#" pintype="input"/>
      <node ref="U8" pin="24" pinfunction="~{OE}" pintype="input"/>
    </net>
    <net code="54" name="/OP2">
      <node ref="J3" pin="8" pinfunction="Pin_8" pintype="passive"/>
      <node ref="U6" pin="28" pinfunction="OP2" pintype="output"/>
    </net>
    <net code="55" name="/OP3">
      <node ref="J3" pin="7" pinfunction="Pin_7" pintype="passive"/>
      <node ref="U6" pin="13" pinfunction="OP3" pintype="output"/>
    </net>
    <net code="56" name="/OP4">
      <node ref="J3" pin="6" pinfunction="Pin_6" pintype="passive"/>
      <node ref="U6" pin="27" pinfunction="OP4" pintype="output"/>
    </net>
    <net code="57" name="/OP5">
      <node ref="J3" pin="5" pinfunction="Pin_5" pintype="passive"/>
      <node ref="U6" pin="14" pinfunction="OP5" pintype="output"/>
    </net>
    <net code="58" name="/OP6">
      <node ref="J3" pin="4" pinfunction="Pin_4" pintype="passive"/>
      <node ref="U6" pin="26" pinfunction="OP6" pintype="output"/>
    </net>
    <net code="59" name="/OP7">
      <node ref="J3" pin="3" pinfunction="Pin_3" pintype="passive"/>
      <node ref="U6" pin="15" pinfunction="OP7" pintype="output"/>
    </net>
    <net code="60" name="/POR*">
      <node ref="R4" pin="2" pintype="passive"/>
      <node ref="SW1" pin="2" pinfunction="2" pintype="passive"/>
      <node ref="U3" pin="8" pinfunction="I8" pintype="input"/>
      <node ref="U4" pin="1" pinfunction="Pin_1" pintype="passive"/>
    </net>
    <net code="61" name="/RAMCS*">
      <node ref="U2" pin="18" pinfunction="IO2" pintype="tri_state"/>
      <node ref="U7" pin="22" pinfunction="CE#" pintype="input"/>
    </net>
    <net code="62" name="/ROMCS*">
      <node ref="U3" pin="15" pinfunction="IO5" pintype="tri_state"/>
      <node ref="U8" pin="22" pinfunction="~{CE}" pintype="input"/>
    </net>
    <net code="63" name="/RTSA*">
      <node ref="J1" pin="12" pinfunction="Pin_12" pintype="passive"/>
      <node ref="U6" pin="29" pinfunction="OP0" pintype="output"/>
    </net>
    <net code="64" name="/RTSB*">
      <node ref="J1" pin="11" pinfunction="Pin_11" pintype="passive"/>
      <node ref="U6" pin="12" pinfunction="OP1" pintype="output"/>
    </net>
    <net code="65" name="/RXA">
      <node ref="J1" pin="10" pinfunction="Pin_10" pintype="passive"/>
      <node ref="U6" pin="11" pinfunction="TXDB" pintype="output"/>
    </net>
    <net code="66" name="/RXB">
      <node ref="J1" pin="9" pinfunction="Pin_9" pintype="passive"/>
      <node ref="U6" pin="10" pinfunction="RXDB" pintype="input"/>
    </net>
    <net code="67" name="/SR_PIN30">
      <node ref="H6" pin="2" pinfunction="Pin_2" pintype="passive"/>
      <node ref="U7" pin="30" pinfunction="A17" pintype="input"/>
    </net>
    <net code="68" name="/SWAP">
      <node ref="U2" pin="13" pinfunction="IO7" pintype="tri_state"/>
      <node ref="U3" pin="14" pinfunction="IO6" pintype="tri_state"/>
    </net>
    <net code="69" name="/TXA">
      <node ref="J1" pin="8" pinfunction="Pin_8" pintype="passive"/>
      <node ref="U6" pin="30" pinfunction="TXDA" pintype="output"/>
    </net>
    <net code="70" name="/TXB">
      <node ref="J1" pin="7" pinfunction="Pin_7" pintype="passive"/>
      <node ref="U6" pin="31" pinfunction="RXDA" pintype="input"/>
    </net>
    <net code="71" name="GND">
      <node ref="C1" pin="1" pintype="passive"/>
      <node ref="C2" pin="1" pintype="passive"/>
      <node ref="C3" pin="1" pintype="passive"/>
      <node ref="C4" pin="1" pintype="passive"/>
      <node ref="C5" pin="1" pintype="passive"/>
      <node ref="C6" pin="1" pintype="passive"/>
      <node ref="C7" pin="2" pintype="passive"/>
      <node ref="C8" pin="2" pintype="passive"/>
      <node ref="C9" pin="1" pintype="passive"/>
      <node ref="H1" pin="1" pinfunction="Pin_1" pintype="passive"/>
      <node ref="H1" pin="3" pinfunction="Pin_3" pintype="passive"/>
      <node ref="H1" pin="5" pinfunction="Pin_5" pintype="passive"/>
      <node ref="H1" pin="7" pinfunction="Pin_7" pintype="passive"/>
      <node ref="J1" pin="1" pinfunction="Pin_1" pintype="passive"/>
      <node ref="J1" pin="2" pinfunction="Pin_2" pintype="passive"/>
      <node ref="J2" pin="6" pinfunction="Pin_6" pintype="passive"/>
      <node ref="J3" pin="1" pinfunction="Pin_1" pintype="passive"/>
      <node ref="SW1" pin="1" pinfunction="1" pintype="passive"/>
      <node ref="U1" pin="7" pinfunction="GND" pintype="power_in"/>
      <node ref="U2" pin="10" pinfunction="GND" pintype="power_in"/>
      <node ref="U3" pin="10" pinfunction="GND" pintype="power_in"/>
      <node ref="U4" pin="3" pinfunction="Pin_3" pintype="passive"/>
      <node ref="U5" pin="15" pinfunction="GND" pintype="power_in"/>
      <node ref="U5" pin="35" pinfunction="GND" pintype="power_in"/>
      <node ref="U6" pin="20" pinfunction="GND" pintype="power_in"/>
      <node ref="U7" pin="16" pinfunction="VSS" pintype="power_in"/>
      <node ref="U8" pin="16" pinfunction="GND" pintype="power_in"/>
    </net>
    <net code="72" name="Net-(C7-Pad1)">
      <node ref="C7" pin="1" pintype="passive"/>
      <node ref="U6" pin="33" pinfunction="X2" pintype="input"/>
      <node ref="Y1" pin="1" pinfunction="1" pintype="passive"/>
    </net>
    <net code="73" name="Net-(C8-Pad1)">
      <node ref="C8" pin="1" pintype="passive"/>
      <node ref="U6" pin="32" pinfunction="X1/CLK" pintype="input"/>
      <node ref="Y1" pin="2" pinfunction="2" pintype="passive"/>
    </net>
    <net code="74" name="Net-(R3-Pad2)">
      <node ref="R3" pin="2" pintype="passive"/>
      <node ref="U5" pin="33" pinfunction="BR" pintype="input"/>
      <node ref="U5" pin="40" pinfunction="BERR" pintype="input"/>
      <node ref="U5" pin="42" pinfunction="IPL0/2" pintype="input"/>
    </net>
    <net code="75" name="VCC">
      <node ref="C1" pin="2" pintype="passive"/>
      <node ref="C2" pin="2" pintype="passive"/>
      <node ref="C3" pin="2" pintype="passive"/>
      <node ref="C4" pin="2" pintype="passive"/>
      <node ref="C5" pin="2" pintype="passive"/>
      <node ref="C6" pin="2" pintype="passive"/>
      <node ref="C9" pin="2" pintype="passive"/>
      <node ref="H1" pin="2" pinfunction="Pin_2" pintype="passive"/>
      <node ref="H1" pin="4" pinfunction="Pin_4" pintype="passive"/>
      <node ref="H1" pin="6" pinfunction="Pin_6" pintype="passive"/>
      <node ref="H1" pin="8" pinfunction="Pin_8" pintype="passive"/>
      <node ref="H2" pin="1" pinfunction="Pin_1" pintype="passive"/>
      <node ref="H3" pin="1" pinfunction="Pin_1" pintype="passive"/>
      <node ref="H4" pin="1" pinfunction="Pin_1" pintype="passive"/>
      <node ref="H5" pin="1" pinfunction="Pin_1" pintype="passive"/>
      <node ref="H6" pin="1" pinfunction="Pin_1" pintype="passive"/>
      <node ref="J1" pin="5" pinfunction="Pin_5" pintype="passive"/>
      <node ref="J1" pin="6" pinfunction="Pin_6" pintype="passive"/>
      <node ref="J2" pin="5" pinfunction="Pin_5" pintype="passive"/>
      <node ref="J3" pin="2" pinfunction="Pin_2" pintype="passive"/>
      <node ref="R1" pin="1" pintype="passive"/>
      <node ref="R2" pin="1" pintype="passive"/>
      <node ref="R3" pin="1" pintype="passive"/>
      <node ref="R4" pin="1" pintype="passive"/>
      <node ref="R5" pin="1" pintype="passive"/>
      <node ref="R6" pin="1" pintype="passive"/>
      <node ref="U1" pin="14" pinfunction="VCC" pintype="power_in"/>
      <node ref="U2" pin="20" pinfunction="VCC" pintype="power_in"/>
      <node ref="U3" pin="20" pinfunction="VCC" pintype="power_in"/>
      <node ref="U4" pin="2" pinfunction="Pin_2" pintype="passive"/>
      <node ref="U5" pin="13" pinfunction="VCC" pintype="power_in"/>
      <node ref="U6" pin="40" pinfunction="VCC" pintype="power_in"/>
      <node ref="U7" pin="32" pinfunction="VCC" pintype="power_in"/>
      <node ref="U8" pin="1" pinfunction="VPP" pintype="input"/>
      <node ref="U8" pin="32" pinfunction="VCC" pintype="power_in"/>
    </net>
    <net code="76" name="unconnected-(U2-Pad17)">
      <node ref="U2" pin="17" pinfunction="I03" pintype="tri_state+no_connect"/>
    </net>
    <net code="77" name="unconnected-(U2-Pad19)">
      <node ref="U2" pin="19" pinfunction="IO1" pintype="tri_state+no_connect"/>
    </net>
    <net code="78" name="unconnected-(U3-Pad11)">
      <node ref="U3" pin="11" pinfunction="I10/~{OE}" pintype="input"/>
    </net>
    <net code="79" name="unconnected-(U3-Pad12)">
      <node ref="U3" pin="12" pinfunction="IO8" pintype="tri_state+no_connect"/>
    </net>
    <net code="80" name="unconnected-(U3-Pad13)">
      <node ref="U3" pin="13" pinfunction="IO7" pintype="tri_state+no_connect"/>
    </net>
    <net code="81" name="unconnected-(U3-Pad17)">
      <node ref="U3" pin="17" pinfunction="I03" pintype="tri_state+no_connect"/>
    </net>
    <net code="82" name="unconnected-(U5-Pad32)">
      <node ref="U5" pin="32" pinfunction="BG" pintype="output+no_connect"/>
    </net>
    <net code="83" name="unconnected-(U5-Pad38)">
      <node ref="U5" pin="38" pinfunction="E" pintype="output+no_connect"/>
    </net>
    <net code="84" name="unconnected-(U5-Pad39)">
      <node ref="U5" pin="39" pinfunction="VPA" pintype="input+no_connect"/>
    </net>
    <net code="85" name="unconnected-(U90-Pad1)">
      <node ref="U90" pin="1" pinfunction="VPP" pintype="input"/>
    </net>
    <net code="86" name="unconnected-(U90-Pad2)">
      <node ref="U90" pin="2" pinfunction="A16" pintype="input"/>
    </net>
    <net code="87" name="unconnected-(U90-Pad3)">
      <node ref="U90" pin="3" pinfunction="A15" pintype="input"/>
    </net>
    <net code="88" name="unconnected-(U90-Pad4)">
      <node ref="U90" pin="4" pinfunction="A12" pintype="input"/>
    </net>
    <net code="89" name="unconnected-(U90-Pad5)">
      <node ref="U90" pin="5" pinfunction="A7" pintype="input"/>
    </net>
    <net code="90" name="unconnected-(U90-Pad6)">
      <node ref="U90" pin="6" pinfunction="A6" pintype="input"/>
    </net>
    <net code="91" name="unconnected-(U90-Pad7)">
      <node ref="U90" pin="7" pinfunction="A5" pintype="input"/>
    </net>
    <net code="92" name="unconnected-(U90-Pad8)">
      <node ref="U90" pin="8" pinfunction="A4" pintype="input"/>
    </net>
    <net code="93" name="unconnected-(U90-Pad9)">
      <node ref="U90" pin="9" pinfunction="A3" pintype="input"/>
    </net>
    <net code="94" name="unconnected-(U90-Pad10)">
      <node ref="U90" pin="10" pinfunction="A2" pintype="input"/>
    </net>
    <net code="95" name="unconnected-(U90-Pad11)">
      <node ref="U90" pin="11" pinfunction="A1" pintype="input"/>
    </net>
    <net code="96" name="unconnected-(U90-Pad12)">
      <node ref="U90" pin="12" pinfunction="A0" pintype="input"/>
    </net>
    <net code="97" name="unconnected-(U90-Pad13)">
      <node ref="U90" pin="13" pinfunction="D0" pintype="tri_state"/>
    </net>
    <net code="98" name="unconnected-(U90-Pad14)">
      <node ref="U90" pin="14" pinfunction="D1" pintype="tri_state"/>
    </net>
    <net code="99" name="unconnected-(U90-Pad15)">
      <node ref="U90" pin="15" pinfunction="D2" pintype="tri_state"/>
    </net>
    <net code="100" name="unconnected-(U90-Pad16)">
      <node ref="U90" pin="16" pinfunction="GND" pintype="power_in"/>
    </net>
    <net code="101" name="unconnected-(U90-Pad17)">
      <node ref="U90" pin="17" pinfunction="D3" pintype="tri_state"/>
    </net>
    <net code="102" name="unconnected-(U90-Pad18)">
      <node ref="U90" pin="18" pinfunction="D4" pintype="tri_state"/>
    </net>
    <net code="103" name="unconnected-(U90-Pad19)">
      <node ref="U90" pin="19" pinfunction="D5" pintype="tri_state"/>
    </net>
    <net code="104" name="unconnected-(U90-Pad20)">
      <node ref="U90" pin="20" pinfunction="D6" pintype="tri_state"/>
    </net>
    <net code="105" name="unconnected-(U90-Pad21)">
      <node ref="U90" pin="21" pinfunction="D7" pintype="tri_state"/>
    </net>
    <net code="106" name="unconnected-(U90-Pad22)">
      <node ref="U90" pin="22" pinfunction="~{CE}" pintype="input"/>
    </net>
    <net code="107" name="unconnected-(U90-Pad23)">
      <node ref="U90" pin="23" pinfunction="A10" pintype="input"/>
    </net>
    <net code="108" name="unconnected-(U90-Pad24)">
      <node ref="U90" pin="24" pinfunction="~{OE}" pintype="input"/>
    </net>
    <net code="109" name="unconnected-(U90-Pad25)">
      <node ref="U90" pin="25" pinfunction="A11" pintype="input"/>
    </net>
    <net code="110" name="unconnected-(U90-Pad26)">
      <node ref="U90" pin="26" pinfunction="A9" pintype="input"/>
    </net>
    <net code="111" name="unconnected-(U90-Pad27)">
      <node ref="U90" pin="27" pinfunction="A8" pintype="input"/>
    </net>
    <net code="112" name="unconnected-(U90-Pad28)">
      <node ref="U90" pin="28" pinfunction="A13" pintype="input"/>
    </net>
    <net code="113" name="unconnected-(U90-Pad29)">
      <node ref="U90" pin="29" pinfunction="A14" pintype="input"/>
    </net>
    <net code="114" name="unconnected-(U90-Pad30)">
      <node ref="U90" pin="30" pinfunction="A17" pintype="input"/>
    </net>
    <net code="115" name="unconnected-(U90-Pad31)">
      <node ref="U90" pin="31" pinfunction="~{PGM}" pintype="input"/>
    </net>
    <net code="116" name="unconnected-(U90-Pad32)">
      <node ref="U90" pin="32" pinfunction="VCC" pintype="power_in"/>
    </net>
    <net code="117" name="unconnected-(U91-Pad1)">
      <node ref="U91" pin="1" pinfunction="VPP" pintype="input"/>
    </net>
    <net code="118" name="unconnected-(U91-Pad2)">
      <node ref="U91" pin="2" pinfunction="A16" pintype="input"/>
    </net>
    <net code="119" name="unconnected-(U91-Pad3)">
      <node ref="U91" pin="3" pinfunction="A15" pintype="input"/>
    </net>
    <net code="120" name="unconnected-(U91-Pad4)">
      <node ref="U91" pin="4" pinfunction="A12" pintype="input"/>
    </net>
    <net code="121" name="unconnected-(U91-Pad5)">
      <node ref="U91" pin="5" pinfunction="A7" pintype="input"/>
    </net>
    <net code="122" name="unconnected-(U91-Pad6)">
      <node ref="U91" pin="6" pinfunction="A6" pintype="input"/>
    </net>
    <net code="123" name="unconnected-(U91-Pad7)">
      <node ref="U91" pin="7" pinfunction="A5" pintype="input"/>
    </net>
    <net code="124" name="unconnected-(U91-Pad8)">
      <node ref="U91" pin="8" pinfunction="A4" pintype="input"/>
    </net>
    <net code="125" name="unconnected-(U91-Pad9)">
      <node ref="U91" pin="9" pinfunction="A3" pintype="input"/>
    </net>
    <net code="126" name="unconnected-(U91-Pad10)">
      <node ref="U91" pin="10" pinfunction="A2" pintype="input"/>
    </net>
    <net code="127" name="unconnected-(U91-Pad11)">
      <node ref="U91" pin="11" pinfunction="A1" pintype="input"/>
    </net>
    <net code="128" name="unconnected-(U91-Pad12)">
      <node ref="U91" pin="12" pinfunction="A0" pintype="input"/>
    </net>
    <net code="129" name="unconnected-(U91-Pad13)">
      <node ref="U91" pin="13" pinfunction="D0" pintype="tri_state"/>
    </net>
    <net code="130" name="unconnected-(U91-Pad14)">
      <node ref="U91" pin="14" pinfunction="D1" pintype="tri_state"/>
    </net>
    <net code="131" name="unconnected-(U91-Pad15)">
      <node ref="U91" pin="15" pinfunction="D2" pintype="tri_state"/>
    </net>
    <net code="132" name="unconnected-(U91-Pad16)">
      <node ref="U91" pin="16" pinfunction="GND" pintype="power_in"/>
    </net>
    <net code="133" name="unconnected-(U91-Pad17)">
      <node ref="U91" pin="17" pinfunction="D3" pintype="tri_state"/>
    </net>
    <net code="134" name="unconnected-(U91-Pad18)">
      <node ref="U91" pin="18" pinfunction="D4" pintype="tri_state"/>
    </net>
    <net code="135" name="unconnected-(U91-Pad19)">
      <node ref="U91" pin="19" pinfunction="D5" pintype="tri_state"/>
    </net>
    <net code="136" name="unconnected-(U91-Pad20)">
      <node ref="U91" pin="20" pinfunction="D6" pintype="tri_state"/>
    </net>
    <net code="137" name="unconnected-(U91-Pad21)">
      <node ref="U91" pin="21" pinfunction="D7" pintype="tri_state"/>
    </net>
    <net code="138" name="unconnected-(U91-Pad22)">
      <node ref="U91" pin="22" pinfunction="~{CE}" pintype="input"/>
    </net>
    <net code="139" name="unconnected-(U91-Pad23)">
      <node ref="U91" pin="23" pinfunction="A10" pintype="input"/>
    </net>
    <net code="140" name="unconnected-(U91-Pad24)">
      <node ref="U91" pin="24" pinfunction="~{OE}" pintype="input"/>
    </net>
    <net code="141" name="unconnected-(U91-Pad25)">
      <node ref="U91" pin="25" pinfunction="A11" pintype="input"/>
    </net>
    <net code="142" name="unconnected-(U91-Pad26)">
      <node ref="U91" pin="26" pinfunction="A9" pintype="input"/>
    </net>
    <net code="143" name="unconnected-(U91-Pad27)">
      <node ref="U91" pin="27" pinfunction="A8" pintype="input"/>
    </net>
    <net code="144" name="unconnected-(U91-Pad28)">
      <node ref="U91" pin="28" pinfunction="A13" pintype="input"/>
    </net>
    <net code="145" name="unconnected-(U91-Pad29)">
      <node ref="U91" pin="29" pinfunction="A14" pintype="input"/>
    </net>
    <net code="146" name="unconnected-(U91-Pad31)">
      <node ref="U91" pin="31" pinfunction="~{PGM}" pintype="input"/>
    </net>
    <net code="147" name="unconnected-(U91-Pad32)">
      <node ref="U91" pin="32" pinfunction="VCC" pintype="power_in"/>
    </net>
    <net code="148" name="unconnected-(U92-Pad1)">
      <node ref="U92" pin="1" pinfunction="A15" pintype="input"/>
    </net>
    <net code="149" name="unconnected-(U92-Pad2)">
      <node ref="U92" pin="2" pinfunction="A12" pintype="input"/>
    </net>
    <net code="150" name="unconnected-(U92-Pad3)">
      <node ref="U92" pin="3" pinfunction="A7" pintype="input"/>
    </net>
    <net code="151" name="unconnected-(U92-Pad4)">
      <node ref="U92" pin="4" pinfunction="A6" pintype="input"/>
    </net>
    <net code="152" name="unconnected-(U92-Pad5)">
      <node ref="U92" pin="5" pinfunction="A5" pintype="input"/>
    </net>
    <net code="153" name="unconnected-(U92-Pad6)">
      <node ref="U92" pin="6" pinfunction="A4" pintype="input"/>
    </net>
    <net code="154" name="unconnected-(U92-Pad7)">
      <node ref="U92" pin="7" pinfunction="A3" pintype="input"/>
    </net>
    <net code="155" name="unconnected-(U92-Pad8)">
      <node ref="U92" pin="8" pinfunction="A2" pintype="input"/>
    </net>
    <net code="156" name="unconnected-(U92-Pad9)">
      <node ref="U92" pin="9" pinfunction="A1" pintype="input"/>
    </net>
    <net code="157" name="unconnected-(U92-Pad10)">
      <node ref="U92" pin="10" pinfunction="A0" pintype="input"/>
    </net>
    <net code="158" name="unconnected-(U92-Pad11)">
      <node ref="U92" pin="11" pinfunction="D0" pintype="tri_state"/>
    </net>
    <net code="159" name="unconnected-(U92-Pad12)">
      <node ref="U92" pin="12" pinfunction="D1" pintype="tri_state"/>
    </net>
    <net code="160" name="unconnected-(U92-Pad13)">
      <node ref="U92" pin="13" pinfunction="D2" pintype="tri_state"/>
    </net>
    <net code="161" name="unconnected-(U92-Pad14)">
      <node ref="U92" pin="14" pinfunction="GND" pintype="power_in"/>
    </net>
    <net code="162" name="unconnected-(U92-Pad15)">
      <node ref="U92" pin="15" pinfunction="D3" pintype="tri_state"/>
    </net>
    <net code="163" name="unconnected-(U92-Pad16)">
      <node ref="U92" pin="16" pinfunction="D4" pintype="tri_state"/>
    </net>
    <net code="164" name="unconnected-(U92-Pad17)">
      <node ref="U92" pin="17" pinfunction="D5" pintype="tri_state"/>
    </net>
    <net code="165" name="unconnected-(U92-Pad18)">
      <node ref="U92" pin="18" pinfunction="D6" pintype="tri_state"/>
    </net>
    <net code="166" name="unconnected-(U92-Pad19)">
      <node ref="U92" pin="19" pinfunction="D7" pintype="tri_state"/>
    </net>
    <net code="167" name="unconnected-(U92-Pad20)">
      <node ref="U92" pin="20" pinfunction="~{CE}" pintype="input"/>
    </net>
    <net code="168" name="unconnected-(U92-Pad21)">
      <node ref="U92" pin="21" pinfunction="A10" pintype="input"/>
    </net>
    <net code="169" name="unconnected-(U92-Pad22)">
      <node ref="U92" pin="22" pinfunction="~{OE}" pintype="input"/>
    </net>
    <net code="170" name="unconnected-(U92-Pad23)">
      <node ref="U92" pin="23" pinfunction="A11" pintype="input"/>
    </net>
    <net code="171" name="unconnected-(U92-Pad24)">
      <node ref="U92" pin="24" pinfunction="A9" pintype="input"/>
    </net>
    <net code="172" name="unconnected-(U92-Pad25)">
      <node ref="U92" pin="25" pinfunction="A8" pintype="input"/>
    </net>
    <net code="173" name="unconnected-(U92-Pad26)">
      <node ref="U92" pin="26" pinfunction="A13" pintype="input"/>
    </net>
    <net code="174" name="unconnected-(U92-Pad27)">
      <node ref="U92" pin="27" pinfunction="A14" pintype="input"/>
    </net>
    <net code="175" name="unconnected-(U92-Pad28)">
      <node ref="U92" pin="28" pinfunction="VCC" pintype="power_in"/>
    </net>
    <net code="176" name="unconnected-(U93-Pad1)">
      <node ref="U93" pin="1" pinfunction="VPP" pintype="input"/>
    </net>
    <net code="177" name="unconnected-(U93-Pad2)">
      <node ref="U93" pin="2" pinfunction="A12" pintype="input"/>
    </net>
    <net code="178" name="unconnected-(U93-Pad3)">
      <node ref="U93" pin="3" pinfunction="A7" pintype="input"/>
    </net>
    <net code="179" name="unconnected-(U93-Pad4)">
      <node ref="U93" pin="4" pinfunction="A6" pintype="input"/>
    </net>
    <net code="180" name="unconnected-(U93-Pad5)">
      <node ref="U93" pin="5" pinfunction="A5" pintype="input"/>
    </net>
    <net code="181" name="unconnected-(U93-Pad6)">
      <node ref="U93" pin="6" pinfunction="A4" pintype="input"/>
    </net>
    <net code="182" name="unconnected-(U93-Pad7)">
      <node ref="U93" pin="7" pinfunction="A3" pintype="input"/>
    </net>
    <net code="183" name="unconnected-(U93-Pad8)">
      <node ref="U93" pin="8" pinfunction="A2" pintype="input"/>
    </net>
    <net code="184" name="unconnected-(U93-Pad9)">
      <node ref="U93" pin="9" pinfunction="A1" pintype="input"/>
    </net>
    <net code="185" name="unconnected-(U93-Pad10)">
      <node ref="U93" pin="10" pinfunction="A0" pintype="input"/>
    </net>
    <net code="186" name="unconnected-(U93-Pad11)">
      <node ref="U93" pin="11" pinfunction="D0" pintype="tri_state"/>
    </net>
    <net code="187" name="unconnected-(U93-Pad12)">
      <node ref="U93" pin="12" pinfunction="D1" pintype="tri_state"/>
    </net>
    <net code="188" name="unconnected-(U93-Pad13)">
      <node ref="U93" pin="13" pinfunction="D2" pintype="tri_state"/>
    </net>
    <net code="189" name="unconnected-(U93-Pad14)">
      <node ref="U93" pin="14" pinfunction="GND" pintype="power_in"/>
    </net>
    <net code="190" name="unconnected-(U93-Pad15)">
      <node ref="U93" pin="15" pinfunction="D3" pintype="tri_state"/>
    </net>
    <net code="191" name="unconnected-(U93-Pad16)">
      <node ref="U93" pin="16" pinfunction="D4" pintype="tri_state"/>
    </net>
    <net code="192" name="unconnected-(U93-Pad17)">
      <node ref="U93" pin="17" pinfunction="D5" pintype="tri_state"/>
    </net>
    <net code="193" name="unconnected-(U93-Pad18)">
      <node ref="U93" pin="18" pinfunction="D6" pintype="tri_state"/>
    </net>
    <net code="194" name="unconnected-(U93-Pad19)">
      <node ref="U93" pin="19" pinfunction="D7" pintype="tri_state"/>
    </net>
    <net code="195" name="unconnected-(U93-Pad20)">
      <node ref="U93" pin="20" pinfunction="~{CE}" pintype="input"/>
    </net>
    <net code="196" name="unconnected-(U93-Pad21)">
      <node ref="U93" pin="21" pinfunction="A10" pintype="input"/>
    </net>
    <net code="197" name="unconnected-(U93-Pad22)">
      <node ref="U93" pin="22" pinfunction="~{OE}" pintype="input"/>
    </net>
    <net code="198" name="unconnected-(U93-Pad23)">
      <node ref="U93" pin="23" pinfunction="A11" pintype="input"/>
    </net>
    <net code="199" name="unconnected-(U93-Pad24)">
      <node ref="U93" pin="24" pinfunction="A9" pintype="input"/>
    </net>
    <net code="200" name="unconnected-(U93-Pad25)">
      <node ref="U93" pin="25" pinfunction="A8" pintype="input"/>
    </net>
    <net code="201" name="unconnected-(U93-Pad26)">
      <node ref="U93" pin="26" pinfunction="A13" pintype="input"/>
    </net>
    <net code="202" name="unconnected-(U93-Pad27)">
      <node ref="U93" pin="27" pinfunction="A14" pintype="input"/>
    </net>
    <net code="203" name="unconnected-(U93-Pad28)">
      <node ref="U93" pin="28" pinfunction="VCC" pintype="power_in"/>
    </net>
    <net code="204" name="unconnected-(U94-Pad1)">
      <node ref="U94" pin="1" pinfunction="VPP" pintype="input"/>
    </net>
    <net code="205" name="unconnected-(U94-Pad2)">
      <node ref="U94" pin="2" pinfunction="A12" pintype="input"/>
    </net>
    <net code="206" name="unconnected-(U94-Pad3)">
      <node ref="U94" pin="3" pinfunction="A7" pintype="input"/>
    </net>
    <net code="207" name="unconnected-(U94-Pad4)">
      <node ref="U94" pin="4" pinfunction="A6" pintype="input"/>
    </net>
    <net code="208" name="unconnected-(U94-Pad5)">
      <node ref="U94" pin="5" pinfunction="A5" pintype="input"/>
    </net>
    <net code="209" name="unconnected-(U94-Pad6)">
      <node ref="U94" pin="6" pinfunction="A4" pintype="input"/>
    </net>
    <net code="210" name="unconnected-(U94-Pad7)">
      <node ref="U94" pin="7" pinfunction="A3" pintype="input"/>
    </net>
    <net code="211" name="unconnected-(U94-Pad8)">
      <node ref="U94" pin="8" pinfunction="A2" pintype="input"/>
    </net>
    <net code="212" name="unconnected-(U94-Pad9)">
      <node ref="U94" pin="9" pinfunction="A1" pintype="input"/>
    </net>
    <net code="213" name="unconnected-(U94-Pad10)">
      <node ref="U94" pin="10" pinfunction="A0" pintype="input"/>
    </net>
    <net code="214" name="unconnected-(U94-Pad11)">
      <node ref="U94" pin="11" pinfunction="D0" pintype="tri_state"/>
    </net>
    <net code="215" name="unconnected-(U94-Pad12)">
      <node ref="U94" pin="12" pinfunction="D1" pintype="tri_state"/>
    </net>
    <net code="216" name="unconnected-(U94-Pad13)">
      <node ref="U94" pin="13" pinfunction="D2" pintype="tri_state"/>
    </net>
    <net code="217" name="unconnected-(U94-Pad14)">
      <node ref="U94" pin="14" pinfunction="GND" pintype="power_in"/>
    </net>
    <net code="218" name="unconnected-(U94-Pad15)">
      <node ref="U94" pin="15" pinfunction="D3" pintype="tri_state"/>
    </net>
    <net code="219" name="unconnected-(U94-Pad16)">
      <node ref="U94" pin="16" pinfunction="D4" pintype="tri_state"/>
    </net>
    <net code="220" name="unconnected-(U94-Pad17)">
      <node ref="U94" pin="17" pinfunction="D5" pintype="tri_state"/>
    </net>
    <net code="221" name="unconnected-(U94-Pad18)">
      <node ref="U94" pin="18" pinfunction="D6" pintype="tri_state"/>
    </net>
    <net code="222" name="unconnected-(U94-Pad19)">
      <node ref="U94" pin="19" pinfunction="D7" pintype="tri_state"/>
    </net>
    <net code="223" name="unconnected-(U94-Pad20)">
      <node ref="U94" pin="20" pinfunction="~{CE}" pintype="input"/>
    </net>
    <net code="224" name="unconnected-(U94-Pad21)">
      <node ref="U94" pin="21" pinfunction="A10" pintype="input"/>
    </net>
    <net code="225" name="unconnected-(U94-Pad22)">
      <node ref="U94" pin="22" pinfunction="~{OE}" pintype="input"/>
    </net>
    <net code="226" name="unconnected-(U94-Pad23)">
      <node ref="U94" pin="23" pinfunction="A11" pintype="input"/>
    </net>
    <net code="227" name="unconnected-(U94-Pad24)">
      <node ref="U94" pin="24" pinfunction="A9" pintype="input"/>
    </net>
    <net code="228" name="unconnected-(U94-Pad25)">
      <node ref="U94" pin="25" pinfunction="A8" pintype="input"/>
    </net>
    <net code="229" name="unconnected-(U94-Pad26)">
      <node ref="U94" pin="26" pinfunction="A13" pintype="input"/>
    </net>
    <net code="230" name="unconnected-(U94-Pad27)">
      <node ref="U94" pin="27" pinfunction="~{PGM}" pintype="input"/>
    </net>
    <net code="231" name="unconnected-(U94-Pad28)">
      <node ref="U94" pin="28" pinfunction="VCC" pintype="power_in"/>
    </net>
    <net code="232" name="unconnected-(U95-Pad1)">
      <node ref="U95" pin="1" pinfunction="VPP" pintype="input"/>
    </net>
    <net code="233" name="unconnected-(U95-Pad2)">
      <node ref="U95" pin="2" pinfunction="A12" pintype="input"/>
    </net>
    <net code="234" name="unconnected-(U95-Pad3)">
      <node ref="U95" pin="3" pinfunction="A7" pintype="input"/>
    </net>
    <net code="235" name="unconnected-(U95-Pad4)">
      <node ref="U95" pin="4" pinfunction="A6" pintype="input"/>
    </net>
    <net code="236" name="unconnected-(U95-Pad5)">
      <node ref="U95" pin="5" pinfunction="A5" pintype="input"/>
    </net>
    <net code="237" name="unconnected-(U95-Pad6)">
      <node ref="U95" pin="6" pinfunction="A4" pintype="input"/>
    </net>
    <net code="238" name="unconnected-(U95-Pad7)">
      <node ref="U95" pin="7" pinfunction="A3" pintype="input"/>
    </net>
    <net code="239" name="unconnected-(U95-Pad8)">
      <node ref="U95" pin="8" pinfunction="A2" pintype="input"/>
    </net>
    <net code="240" name="unconnected-(U95-Pad9)">
      <node ref="U95" pin="9" pinfunction="A1" pintype="input"/>
    </net>
    <net code="241" name="unconnected-(U95-Pad10)">
      <node ref="U95" pin="10" pinfunction="A0" pintype="input"/>
    </net>
    <net code="242" name="unconnected-(U95-Pad11)">
      <node ref="U95" pin="11" pinfunction="D0" pintype="tri_state"/>
    </net>
    <net code="243" name="unconnected-(U95-Pad12)">
      <node ref="U95" pin="12" pinfunction="D1" pintype="tri_state"/>
    </net>
    <net code="244" name="unconnected-(U95-Pad13)">
      <node ref="U95" pin="13" pinfunction="D2" pintype="tri_state"/>
    </net>
    <net code="245" name="unconnected-(U95-Pad14)">
      <node ref="U95" pin="14" pinfunction="GND" pintype="power_in"/>
    </net>
    <net code="246" name="unconnected-(U95-Pad15)">
      <node ref="U95" pin="15" pinfunction="D3" pintype="tri_state"/>
    </net>
    <net code="247" name="unconnected-(U95-Pad16)">
      <node ref="U95" pin="16" pinfunction="D4" pintype="tri_state"/>
    </net>
    <net code="248" name="unconnected-(U95-Pad17)">
      <node ref="U95" pin="17" pinfunction="D5" pintype="tri_state"/>
    </net>
    <net code="249" name="unconnected-(U95-Pad18)">
      <node ref="U95" pin="18" pinfunction="D6" pintype="tri_state"/>
    </net>
    <net code="250" name="unconnected-(U95-Pad19)">
      <node ref="U95" pin="19" pinfunction="D7" pintype="tri_state"/>
    </net>
    <net code="251" name="unconnected-(U95-Pad20)">
      <node ref="U95" pin="20" pinfunction="~{CE}" pintype="input"/>
    </net>
    <net code="252" name="unconnected-(U95-Pad21)">
      <node ref="U95" pin="21" pinfunction="A10" pintype="input"/>
    </net>
    <net code="253" name="unconnected-(U95-Pad22)">
      <node ref="U95" pin="22" pinfunction="~{OE}" pintype="input"/>
    </net>
    <net code="254" name="unconnected-(U95-Pad23)">
      <node ref="U95" pin="23" pinfunction="A11" pintype="input"/>
    </net>
    <net code="255" name="unconnected-(U95-Pad24)">
      <node ref="U95" pin="24" pinfunction="A9" pintype="input"/>
    </net>
    <net code="256" name="unconnected-(U95-Pad25)">
      <node ref="U95" pin="25" pinfunction="A8" pintype="input"/>
    </net>
    <net code="257" name="unconnected-(U95-Pad26)">
      <node ref="U95" pin="26" pinfunction="NC" pintype="no_connect"/>
    </net>
    <net code="258" name="unconnected-(U95-Pad27)">
      <node ref="U95" pin="27" pinfunction="~{PGM}" pintype="input"/>
    </net>
    <net code="259" name="unconnected-(U95-Pad28)">
      <node ref="U95" pin="28" pinfunction="VCC" pintype="power_in"/>
    </net>
  </nets>
</export>
